Workbook

Sheet Инструкция
A1: Финансовая модель запуска «Точки Чистоты» (cleanliness.pro) в Тюмени
A3: Горизонт: 24 месяца, M1 = ноябрь 2026. Суммы в рублях.
A5: Как пользоваться:
A6: 1. Меняйте только ячейки с СИНИМ шрифтом на листах «Допущения» и «Сценарии».
A7: Жёлтая заливка — ключевые допущения, сильнее всего влияющие на результат.
A8: 2. Листы «Юнит-экономика», «ОПиУ_*» и «Сводка» считаются формулами автоматически.
A9: 3. Сценарии отличаются только объёмами, оттоком и CAC (лист «Сценарии»); цены и затраты на заказ общие.
A10: 4. Модель считается на РЕКОМЕНДУЕМОМ прайсе. Прежний прайс сайта (сиды до обновления) — для сравнения на листе «Юнит-экономика».
A12: Цветовая легенда:
A13: синий шрифт — ввод; чёрный — формула; зелёный — ссылка на другой лист; жёлтая заливка — ключевое допущение.
A15: Логика ОПиУ (по месяцам):
A16: Выручка = заказы A × чек A + визиты B × цена визита + спецуслуги × чек S + B2B-договоры × сумма договора
... A25: Источник цифр: strategy/model/assumptions.py. Сборка: python3 strategy/model/build_finmodel.py

Sheet Сводка
A1: Сводка по сценариям
A3: Показатель | B3: Пессимистичный | C3: Реалистичный | D3: Оптимистичный | E3: Комментарий
A4: Выручка за первые 12 мес | B4: =SUM(ОПиУ_Пессимист!C23:N23) -> 7371857 | C4: =SUM(ОПиУ_Реалист!C23:N23) -> 14560374 | D4: =SUM(ОПиУ_Оптимист!C23:N23) -> 21686438
A5: Выручка за 24 мес | B5: =ОПиУ_Пессимист!B23 -> 21462321 | C5: =ОПиУ_Реалист!B23 -> 49127822 | D5: =ОПиУ_Оптимист!B23 -> 77114080
A6: Выручка в M12 (окт 2027) | B6: =ОПиУ_Пессимист!N23 -> 932305.95 | C6: =ОПиУ_Реалист!N23 -> 2022220.4 | D6: =ОПиУ_Оптимист!N23 -> 3106776.3
A7: Выручка в M24 (окт 2028) | B7: =ОПиУ_Пессимист!Z23 -> 1297561.5 | C7: =ОПиУ_Реалист!Z23 -> 3525380.9 | D7: =ОПиУ_Оптимист!Z23 -> 5837246.6
A8: Операционная прибыль за 12 мес | B8: =SUM(ОПиУ_Пессимист!C31:N31) -> -414585.79 | C8: =SUM(ОПиУ_Реалист!C31:N31) -> 1277817.9 | D8: =SUM(ОПиУ_Оптимист!C31:N31) -> 3223063.1
A9: Операционная прибыль за 24 мес | B9: =ОПиУ_Пессимист!B31 -> 995249.55 | C9: =ОПиУ_Реалист!B31 -> 7072084.3 | D9: =ОПиУ_Оптимист!B31 -> 12265917
A10: Операционная прибыль в M12 | B10: =ОПиУ_Пессимист!N31 -> 50937.958 | C10: =ОПиУ_Реалист!N31 -> 299822.3 | D10: =ОПиУ_Оптимист!N31 -> 557360.71
A11: Операционная прибыль в M24 | B11: =ОПиУ_Пессимист!Z31 -> 151302.36 | C11: =ОПиУ_Реалист!Z31 -> 500075.43 | D11: =ОПиУ_Оптимист!Z31 -> 1028239.2
A12: Рентабельность за 24 мес | B12: =ОПиУ_Пессимист!B32 -> 0.046371943 | C12: =ОПиУ_Реалист!B32 -> 0.14395273 | D12: =ОПиУ_Оптимист!B32 -> 0.15906196
A13: Месяц устойчивой безубыточности | B13: =IF(MIN(ОПиУ_Пессимист!C39:Z39)=0,"> 24",MIN(ОПиУ_Пессимист!C39:Z39)) -> 7 | C13: =IF(MIN(ОПиУ_Реалист!C39:Z39)=0,"> 24",MIN(ОПиУ_Реалист!C39:Z39)) -> 5 | D13: =IF(MIN(ОПиУ_Оптимист!C39:Z39)=0,"> 24",MIN(ОПиУ_Оптимист!C39:Z39)) -> 4 | E13: Первый месяц, начиная с которого нет убыточных месяцев
A14: Срок окупаемости вложений, мес | B14: =IF(_xlfn.MINIFS(ОПиУ_Пессимист!C3:Z3,ОПиУ_Пессимист!C38:Z38,">=0")=0,"> 24",_xlfn.MINIFS(ОПиУ_Пессимист!C3:Z3,ОПиУ_Пессимист!C38:Z38,">=0")) -> 24 | C14: =IF(_xlfn.MINIFS(ОПиУ_Реалист!C3:Z3,ОПиУ_Реалист!C38:Z38,">=0")=0,"> 24",_xlfn.MINIFS(ОПиУ_Реалист!C3:Z3,ОПиУ_Реалист!C38:Z38,">=0")) -> 11 | D14: =IF(_xlfn.MINIFS(ОПиУ_Оптимист!C3:Z3,ОПиУ_Оптимист!C38:Z38,">=0")=0,"> 24",_xlfn.MINIFS(ОПиУ_Оптимист!C3:Z3,ОПиУ_Оптимист!C38:Z38,">=0")) -> 8 | E14: Накопленный ДП с учётом CAPEX и предзапуска ≥ 0
A15: Максимальный кассовый разрыв (операционный) | B15: =-MIN(0,MIN(ОПиУ_Пессимист!C37:Z37)) -> 853486.73 | C15: =-MIN(0,MIN(ОПиУ_Реалист!C37:Z37)) -> 388177.52 | D15: =-MIN(0,MIN(ОПиУ_Оптимист!C37:Z37)) -> 355125.17 | E15: Без стартовых вложений; включает CAPEX 2-го этапа
A16: Минимум накопленного ДП (с вложениями) | B16: =MIN(ОПиУ_Пессимист!C38:Z38) -> -1427486.7 | C16: =MIN(ОПиУ_Реалист!C38:Z38) -> -962177.52 | D16: =MIN(ОПиУ_Оптимист!C38:Z38) -> -929125.17 | E16: Пиковая потребность в деньгах
A17: Первый месяц с НДС 5% | B17: =IF(_xlfn.MINIFS(ОПиУ_Пессимист!C3:Z3,ОПиУ_Пессимист!C28:Z28,1)=0,"нет",_xlfn.MINIFS(ОПиУ_Пессимист!C3:Z3,ОПиУ_Пессимист!C28:Z28,1)) -> нет | C17: =IF(_xlfn.MINIFS(ОПиУ_Реалист!C3:Z3,ОПиУ_Реалист!C28:Z28,1)=0,"нет",_xlfn.MINIFS(ОПиУ_Реалист!C3:Z3,ОПиУ_Реалист!C28:Z28,1)) -> 23 | D17: =IF(_xlfn.MINIFS(ОПиУ_Оптимист!C3:Z3,ОПиУ_Оптимист!C28:Z28,1)=0,"нет",_xlfn.MINIFS(ОПиУ_Оптимист!C3:Z3,ОПиУ_Оптимист!C28:Z28,1)) -> 13 | E17: Порог 20 млн ₽ выручки в календарный год
A18: Активные подписчики в M24 | B18: =ОПиУ_Пессимист!Z12 -> 61.781625 | C18: =ОПиУ_Реалист!Z12 -> 190.96475 | D18: =ОПиУ_Оптимист!Z12 -> 331.36099
A19: Клинеров (FTE) в M12 | B19: =ОПиУ_Пессимист!N16 -> 6.9132484 | C19: =ОПиУ_Реалист!N16 -> 15.443595 | D19: =ОПиУ_Оптимист!N16 -> 23.866086
A20: Клинеров (FTE) в M24 | B20: =ОПиУ_Пессимист!Z16 -> 10.008828 | C20: =ОПиУ_Реалист!Z16 -> 26.805249 | D20: =ОПиУ_Оптимист!Z16 -> 43.395585
A22: Стартовый капитал | B22: Минимальный | C22: Рекомендуемый | E22: Комментарий
A23: CAPEX: оборудование, брендинг, сайт | B23: =capex_base -> 472000 | C23: =capex_base -> 472000 | E23: Лист «Допущения»
A24: Предзапуск: рекрутинг, стажировка, юрист, стартовое продвижение | B24: =prelaunch_total -> 102000 | C24: =prelaunch_total -> 102000
A25: Резерв на кассовый разрыв | B25: =max_gap_R*reserve_safety -> 465813.03 | C25: =max_gap_P*reserve_safety -> 1024184.1 | E25: Мин. — по реалистичному, рекоменд. — по пессимистичному сценарию × запас
A26: ИТОГО порог входа | B26: =SUM(B23:B25) -> 1039813 | C26: =SUM(C23:C25) -> 1598184.1
A28: Точка безубыточности (FIX базовый) | B28: Пессимистичный | C28: Реалистичный | D28: Оптимистичный | E28: Комментарий
A29: FIX базовый, ₽/мес | B29: =fix_base -> 179600 | C29: =fix_base -> 179600 | D29: =fix_base -> 179600
A30: Маржинальный доход заказа A после CAC | B30: =cm_a-sc_cac_a_P -> 3617.5 | C30: =cm_a-sc_cac_a_R -> 4017.5 | D30: =cm_a-sc_cac_a_O -> 4217.5
A31: Только заказы A, шт/мес | B31: =fix_base/(cm_a-sc_cac_a_P) -> 49.647547 | C31: =fix_base/(cm_a-sc_cac_a_R) -> 44.704418 | D31: =fix_base/(cm_a-sc_cac_a_O) -> 42.584469 | E31: Если весь доход — от генеральных/после ремонта
A32: … в день | B32: =fix_base/(cm_a-sc_cac_a_P)/30 -> 1.6549182 | C32: =fix_base/(cm_a-sc_cac_a_R)/30 -> 1.4901473 | D32: =fix_base/(cm_a-sc_cac_a_O)/30 -> 1.4194823
A33: Только подписка: визитов в месяц | B33: =fix_base/cm_b -> 168.0515 | C33: =fix_base/cm_b -> 168.0515 | D33: =fix_base/cm_b -> 168.0515 | E33: CAC подписчика окупается за 1–2 мес, здесь не учтён
A34: … это активных подписчиков | B34: =fix_base/cm_b/UB_visits_per_month -> 60.018393 | C34: =fix_base/cm_b/UB_visits_per_month -> 60.018393 | D34: =fix_base/cm_b/UB_visits_per_month -> 60.018393
A35: Микс: при 30 активных подписчиках нужно заказов A | B35: =MAX(0,(fix_base-30*cm_month_b)/(cm_a-sc_cac_a_P)) -> 24.831381 | C35: =MAX(0,(fix_base-30*cm_month_b)/(cm_a-sc_cac_a_R)) -> 22.359059 | D35: =MAX(0,(fix_base-30*cm_month_b)/(cm_a-sc_cac_a_O)) -> 21.29876 | E35: Подписка закрывает половину FIX, остальное — заказы A

Sheet Допущения
A1: Допущения модели
A3: Параметр | B3: Значение | C3: Ед. | D3: Источник / комментарий
A4: Календарь
A5: Год начала (M1) | B5: 2026 | C5: год | D5: M1 = ноябрь 2026
A6: Месяц начала (M1) | B6: 11 | C6: мес
A7: Налоги и платежи
A8: Ставка УСН «доходы» | B8: 0.06 | C8: % | D8: УСН «доходы» 6% (без уменьшения на взносы — консервативно)
A9: Порог освобождения от НДС | B9: 20000000 | C9: ₽/год | D9: Порог освобождения от НДС на УСН 2026–2028: 20 млн ₽ (закон от 04.07.2026 № 228-ФЗ, см. moysklad.ru/news/porog-dokhoda-dlya-nds-na-usn)
A10: Ставка НДС для УСН сверх порога | B10: 0.05 | C10: % | D10: Пониженная ставка НДС для УСН при превышении порога: 5% (выделяется из цены)
A11: Эквайринг / СБП | B11: 0.015 | C11: % чека | D11: Эквайринг/СБП средневзвешенно: СБП ~0,4–0,7%, карты ~2–2,5%
A12: Юнит A — генеральная / после ремонта
A13: Площадь типового объекта | B13: 60 | C13: м² | D13: Типовой объект: 2-комн. (евро-3) в новостройке Тюмени, м²
A14: Цена генеральной | B14: 180 | C14: ₽/м² | D14: Генеральная, ₽/м². Рынок Тюмени: от 170 ₽/м² (KP.ru, рейтинг клининга Тюмени 2026)
A15: Цена уборки после ремонта | B15: 230 | C15: ₽/м² | D15: После ремонта, ₽/м². Рынок Тюмени: от 190 ₽/м² (KP.ru); средний рынок 200–300 ₽/м²
A16: Доля «после ремонта» в типе A | B16: 0.5 | C16: % | D16: Доля заказов «после ремонта» в типе A
A17: Средний допчек | B17: 1200 | C17: ₽ | D17: Средний допчек: окна/балкон, духовка/холодильник внутри, люстры
A18: Трудоёмкость заказа | B18: 14 | C18: чел-ч | D18: Трудоёмкость: генеральная ~12 чел-ч, после ремонта ~16 чел-ч (бригада из 2 чел.)
A19: Оплата клинеров | B19: 0.4 | C19: % чека | D19: Оплата клинеров, % от чека (сдельно, самозанятые/ГПХ)
A20: Химия и расходники | B20: 550 | C20: ₽/заказ | D20: Химия + расходники на выезд (пады, мешки, салфетки), ₽
A21: Амортизация оборудования | B21: 250 | C21: ₽/заказ | D21: Амортизация оборудования на заказ, ₽
A22: Логистика | B22: 800 | C22: ₽/заказ | D22: Такси туда-обратно для бригады с инвентарём / компенсация авто, ₽
A23: Резерв качества | B23: 0.02 | C23: % чека | D23: Резерв на переделки/компенсации порчи, % от чека
A24: Юнит B — поддерживающая (подписка)
A25: Площадь типового объекта | B25: 55 | C25: м² | D25: Типовой объект: 2-комн., м²
A26: Цена разовой поддерживающей | B26: 3900 | C26: ₽ | D26: Разовая поддерживающая 2-комн. Рынок: 3 500–4 500 ₽ (Профи.ру ср. 3 500 ₽; budet-chisto: 2к до 53 м² от 4 000 ₽)
A27: Средняя скидка подписки | B27: 0.12 | C27: % | D27: Средняя скидка подписки: раз в неделю −15%, раз в 2 недели −10%
A28: Длительность визита | B28: 3.5 | C28: ч | D28: Длительность визита, ч (1 клинер)
A29: Оплата клинера | B29: 0.45 | C29: % чека | D29: Оплата клинера, % от чека визита
A30: Химия и расходники | B30: 150 | C30: ₽/визит | D30: Химия/расходники на визит, ₽
A31: Амортизация инвентаря | B31: 60 | C31: ₽/визит | D31: Амортизация инвентаря на визит, ₽
A32: Проезд клинера | B32: 300 | C32: ₽/визит | D32: Компенсация проезда клинеру, ₽
A33: Резерв качества | B33: 0.015 | C33: % чека | D33: Резерв качества, % от чека
A34: Визитов на подписчика в месяц | B34: 2.8 | C34: визитов | D34: Среднее число визитов на подписчика в месяц (микс 1 раз/нед и 1 раз/2 нед)
A35: Юнит S — спецуслуги (химчистка мебели, окна)
A36: Средний чек спецуслуги | B36: 4500 | C36: ₽ | D36: Средний чек: диван + кресло/матрас или окна 2-комн. Рынок: диван 1 500–2 660 ₽ (Профи.ру ср. 2 660 ₽)
A37: Трудоёмкость | B37: 3 | C37: чел-ч | D37: Трудоёмкость, чел-ч
A38: Оплата мастера | B38: 0.35 | C38: % чека | D38: Оплата мастера, % от чека
A39: Химия | B39: 300 | C39: ₽/заказ | D39: Химия, ₽
A40: Амортизация | B40: 350 | C40: ₽/заказ | D40: Амортизация экстрактора/оборудования, ₽
A41: Логистика | B41: 400 | C41: ₽/заказ | D41: Логистика, ₽
A42: Резерв качества | B42: 0.015 | C42: % чека | D42: Резерв качества, % от чека
A43: B2B — обслуживание офисов по договору
A44: Сумма договора | B44: 55000 | C44: ₽/мес | D44: Ежемесячный договор: офис ~250–300 м², 5/2, вечерняя уборка, ₽/мес
A45: Прямые затраты | B45: 0.68 | C45: % выручки | D45: Прямые затраты (ФОТ штатного клинера, химия, расходники), % выручки
A46: Прежний прайс Тюмени (seed.py на ревизии 0be802d) — для сравнения
A47: Типовой объект: комнат | B47: 2 | C47: шт | D47: Тариф = база + комнаты × ставка + санузлы × ставка
A48: Типовой объект: санузлов | B48: 1 | C48: шт
A49: Поддерживающая: база | B49: 1500 | C49: ₽ | D49: Сиды проекта до обновления, город tyumen
A50: Поддерживающая: за комнату | B50: 450 | C50: ₽
A51: Поддерживающая: за санузел | B51: 350 | C51: ₽
A52: Поддерживающая: норма времени на объект | B52: 145 | C52: мин | D52: minutes_base + комнаты × мин + санузлы × мин (из сидов)
A53: Генеральная: база | B53: 3500 | C53: ₽ | D53: Сиды проекта до обновления, город tyumen
A54: Генеральная: за комнату | B54: 900 | C54: ₽
A55: Генеральная: за санузел | B55: 700 | C55: ₽
A56: Генеральная: норма времени на объект | B56: 285 | C56: мин | D56: minutes_base + комнаты × мин + санузлы × мин (из сидов)
A57: После ремонта: база | B57: 5000 | C57: ₽ | D57: Сиды проекта до обновления, город tyumen
A58: После ремонта: за комнату | B58: 1300 | C58: ₽
A59: После ремонта: за санузел | B59: 1000 | C59: ₽
A60: После ремонта: норма времени на объект | B60: 420 | C60: мин | D60: minutes_base + комнаты × мин + санузлы × мин (из сидов)
A61: Персонал и целевые ориентиры
A62: Продуктивных часов клинера в месяц | B62: 150 | C62: ч | D62: Продуктивных часов клинера в месяц (FTE)
A63: Клинеров на 1 B2B-договор | B63: 1 | C63: FTE | D63: Штатных клинеров на 1 B2B-договор
A64: Целевая маржа заказа A после CAC | B64: 0.25 | C64: % чека | D64: Целевая маржа заказа A после CAC (до FIX), % от чека
A65: Минимальный LTV / CAC | B65: 3 | C65: x | D65: Минимальный LTV/CAC для подписки
A66: Макс. окупаемость CAC подписчика | B66: 3 | C66: мес | D66: Максимальный срок окупаемости CAC подписчика, мес
A67: Конверсия лида в заказ A | B67: 0.4 | C67: % | D67: Конверсия лида в заказ A (после ремонта/генеральная)
A68: Конверсия пробной уборки в подписку | B68: 0.25 | C68: % | D68: Конверсия первой поддерживающей уборки в подписку
A69: Сезонность разовых заказов (индекс по календарному месяцу)
A70: 01 — янв | B70: 0.7 | C70: индекс | D70: Экспертная оценка для Тюмени: провал янв–фев, пики апр–май, авг–сен, дек
A71: 02 — фев | B71: 0.8 | C71: индекс
A72: 03 — мар | B72: 0.95 | C72: индекс
A73: 04 — апр | B73: 1.15 | C73: индекс
A74: 05 — май | B74: 1.25 | C74: индекс
A75: 06 — июн | B75: 1.1 | C75: индекс
A76: 07 — июл | B76: 0.9 | C76: индекс
A77: 08 — авг | B77: 1.05 | C77: индекс
A78: 09 — сен | B78: 1.1 | C78: индекс
A79: 10 — окт | B79: 1 | C79: индекс
A80: 11 — ноя | B80: 0.95 | C80: индекс
A81: 12 — дек | B81: 1.2 | C81: индекс
A82: Постоянные расходы (FIX), ₽/мес
A83: Администратор-диспетчер / продажи (оклад + KPI, с взносами; можно делить с Уфой) | B83: 70000 | C83: ₽/мес
A84: Бригадир-контролёр качества (фикс-часть; сдельная — в COGS) | B84: 25000 | C84: ₽/мес
A85: Кладовая инвентаря 15–20 м² + коммуналка | B85: 15000 | C85: ₽/мес
A86: Телефония и коллтрекинг, SMS, доля хостинга (CRM своя) | B86: 9000 | C86: ₽/мес
A87: Яндекс Бизнес, расширенный тариф (~18 270 ₽ / 90 дней) | B87: 6100 | C87: ₽/мес
A88: Авито: тариф/базовое продвижение | B88: 10000 | C88: ₽/мес
A89: SEO и контент (копирайтер, фото, PR-размещения) | B89: 25000 | C89: ₽/мес
A90: Бухгалтерия на аутсорсе + ЭДО | B90: 9000 | C90: ₽/мес
A91: Страхование гражданской ответственности | B91: 2500 | C91: ₽/мес
A92: Хозрасходы, обучение, непредвиденные | B92: 8000 | C92: ₽/мес
A93: FIX базовый, итого | B93: =SUM(B83:B92) -> 179600 | D93: Без вознаграждения собственника
A94: Доп. накладные на ступень выручки | B94: 70000 | C94: ₽/мес | D94: Доп. накладные на каждую ступень выручки (2-й диспетчер, контролёр, склад)
A95: Ступень выручки | B95: 1500000 | C95: ₽/мес | D95: Ступень выручки в месяц, ₽
A96: CAPEX — стартовое оборудование и запуск (M0). Цены — ориентиры 2026, проверить у поставщиков
A97: Позиция | B97: Цена за ед., ₽ | C97: Кол-во | D97: Сумма, ₽
A98: Экстрактор для химчистки мебели (класс Karcher Puzzi 10/1) | B98: 55000 | C98: 1 | D98: =B98*C98 -> 55000
A99: Пылесос строительный для уборки после ремонта (класс NT 30/1, фильтр L) | B99: 40000 | C99: 1 | D99: =B99*C99 -> 40000
A100: Пылесос профессиональный сухой уборки (класс T 10/1) | B100: 22000 | C100: 2 | D100: =B100*C100 -> 44000
A101: Парогенератор (класс SC 4/SC 5) | B101: 30000 | C101: 2 | D101: =B101*C101 -> 60000
...

Sheet Сценарии
A1: Сценарии: объёмы, отток, CAC
A3: Параметр | B3: Пессимистичный | C3: Реалистичный | D3: Оптимистичный
A4: Заказы A в M1, шт/мес (до сезонности) | B4: 8 | C4: 12 | D4: 18
A5: Заказы A в M6, шт/мес (до сезонности) | B5: 28 | C5: 45 | D5: 60
A6: Рост заказов A с M7, %/мес | B6: 0.02 | C6: 0.04 | D6: 0.05
A7: Потолок мощности по A, шт/мес | B7: 60 | C7: 110 | D7: 140
A8: Новые подписчики B в M1, чел/мес | B8: 2 | C8: 4 | D8: 6
A9: Новые подписчики B в M6, чел/мес | B9: 7 | C9: 14 | D9: 20
A10: Рост притока подписчиков с M7, %/мес | B10: 0.01 | C10: 0.03 | D10: 0.035
A11: Отток подписчиков, %/мес | B11: 0.12 | C11: 0.09 | D11: 0.07
A12: Спецуслуги (химчистка/окна) на 1 заказ A | B12: 0.3 | C12: 0.45 | D12: 0.6
A13: Месяц первого B2B-договора | B13: 7 | C13: 4 | D13: 3
A14: Новый B2B-договор каждые N мес | B14: 6 | C14: 3 | D14: 2
A15: Максимум B2B-договоров | B15: 2 | C15: 5 | D15: 7
... A19: Месяц покупки оборудования 2-го этапа | B19: 10 | C19: 6 | D19: 4

Sheet Юнит-экономика
A1: Юнит-экономика по типам заказов
A3: Тип A — генеральная / после ремонта | B3: ₽ / значение | C3: % от чека | D3: Комментарий
A4: Средневзвешенная цена, ₽/м² | B4: =UA_price_general_m2*(1-UA_share_repair)+UA_price_repair_m2*UA_share_repair -> 205
A5: Средний чек (AOV) | B5: =UA_area*price_m2_a+UA_upsell -> 13500 | C5: =IF(aov_a=0,0,B5/aov_a) -> 1 | D5: Площадь × цена + допчек
A6: Оплата клинеров | B6: =aov_a*UA_labor_share -> 5400 | C6: =IF(aov_a=0,0,B6/aov_a) -> 0.4
A7: Химия и расходники | B7: =UA_chem -> 550 | C7: =IF(aov_a=0,0,B7/aov_a) -> 0.040740741
A8: Амортизация оборудования | B8: =UA_amort -> 250 | C8: =IF(aov_a=0,0,B8/aov_a) -> 0.018518519
A9: Логистика | B9: =UA_logistics -> 800 | C9: =IF(aov_a=0,0,B9/aov_a) -> 0.059259259
A10: Эквайринг / СБП | B10: =aov_a*acquiring -> 202.5 | C10: =IF(aov_a=0,0,B10/aov_a) -> 0.015
A11: Резерв качества (переделки, компенсации) | B11: =aov_a*UA_quality_reserve -> 270 | C11: =IF(aov_a=0,0,B11/aov_a) -> 0.02
A12: Переменные затраты (COGS) | B12: =SUM(B6:B11) -> 7472.5 | C12: =IF(aov_a=0,0,B12/aov_a) -> 0.55351852
A13: Валовая прибыль | B13: =aov_a-var_a -> 6027.5 | C13: =IF(aov_a=0,0,B13/aov_a) -> 0.44648148
A14: УСН | B14: =aov_a*usn_rate -> 810 | C14: =IF(aov_a=0,0,B14/aov_a) -> 0.06
A15: Маржинальный доход до CAC | B15: =gm_a-B14 -> 5217.5 | C15: =IF(aov_a=0,0,B15/aov_a) -> 0.38648148 | D15: Сколько заказ приносит на покрытие FIX и маркетинга
A16: Оплата клинера за чел-час | B16: =labor_a/UA_man_hours -> 385.71429 | D16: Ориентир рынка Тюмени: 300–450 ₽/ч
A17: Оплата клинеров за м² | B17: =labor_a/UA_area -> 90
A18: Допустимый CAC при целевой марже | B18: =cm_a-target_margin_a*aov_a -> 1842.5 | C18: =IF(aov_a=0,0,B18/aov_a) -> 0.13648148 | D18: Маржа после CAC не ниже целевой
A19: CAC безубыточности заказа | B19: =cm_a -> 5217.5 | C19: =IF(aov_a=0,0,B19/aov_a) -> 0.38648148 | D19: Выше — каждый заказ в минус
A20: Допустимая цена лида (CPL) | B20: =cac_max_a*lead_to_order_a -> 737 | D20: При конверсии лид → заказ из «Допущений»
A22: Тип B — поддерживающая (подписка), на 1 визит | B22: ₽ / значение | C22: % от чека | D22: Комментарий
A23: Цена визита по подписке | B23: =UB_price_single*(1-UB_sub_discount) -> 3432 | C23: =IF(price_b=0,0,B23/price_b) -> 1 | D23: Разовая цена − средняя скидка подписки
A24: Оплата клинера | B24: =price_b*UB_labor_share -> 1544.4 | C24: =IF(price_b=0,0,B24/price_b) -> 0.45
A25: Химия и расходники | B25: =UB_chem -> 150 | C25: =IF(price_b=0,0,B25/price_b) -> 0.043706294
A26: Амортизация инвентаря | B26: =UB_amort -> 60 | C26: =IF(price_b=0,0,B26/price_b) -> 0.017482517
A27: Проезд клинера | B27: =UB_logistics -> 300 | C27: =IF(price_b=0,0,B27/price_b) -> 0.087412587
A28: Эквайринг / СБП | B28: =price_b*acquiring -> 51.48 | C28: =IF(price_b=0,0,B28/price_b) -> 0.015
A29: Резерв качества | B29: =price_b*UB_quality_reserve -> 51.48 | C29: =IF(price_b=0,0,B29/price_b) -> 0.015
A30: Переменные затраты на визит | B30: =SUM(B24:B29) -> 2157.36 | C30: =IF(price_b=0,0,B30/price_b) -> 0.6286014
A31: Валовая прибыль на визит | B31: =price_b-var_b -> 1274.64 | C31: =IF(price_b=0,0,B31/price_b) -> 0.3713986
A32: УСН | B32: =price_b*usn_rate -> 205.92 | C32: =IF(price_b=0,0,B32/price_b) -> 0.06
A33: Маржинальный доход на визит | B33: =gm_b-B32 -> 1068.72 | C33: =IF(price_b=0,0,B33/price_b) -> 0.3113986
A34: Оплата клинера за час | B34: =labor_b/UB_hours -> 441.25714
A35: Выручка с подписчика в месяц | B35: =price_b*UB_visits_per_month -> 9609.6
A36: Маржинальный доход с подписчика в месяц | B36: =cm_b*UB_visits_per_month -> 2992.416
A38: LTV подписчика по сценариям | B38: Пессимистичный | C38: Реалистичный | D38: Оптимистичный
A39: Отток в месяц | B39: =sc_churn_P -> 0.12 | C39: =sc_churn_R -> 0.09 | D39: =sc_churn_O -> 0.07
A40: Средний срок жизни, мес (1 / отток) | B40: =1/sc_churn_P -> 8.3333333 | C40: =1/sc_churn_R -> 11.111111 | D40: =1/sc_churn_O -> 14.285714
A41: LTV по выручке | B41: =rev_month_b/sc_churn_P -> 80080 | C41: =rev_month_b/sc_churn_R -> 106773.33 | D41: =rev_month_b/sc_churn_O -> 137280
A42: LTV по маржинальному доходу | B42: =cm_month_b/sc_churn_P -> 24936.8 | C42: =cm_month_b/sc_churn_R -> 33249.067 | D42: =cm_month_b/sc_churn_O -> 42748.8
A43: Макс. CAC при LTV/CAC ≥ цели | B43: =cm_month_b/sc_churn_P/ltv_cac_min -> 8312.2667 | C43: =cm_month_b/sc_churn_R/ltv_cac_min -> 11083.022 | D43: =cm_month_b/sc_churn_O/ltv_cac_min -> 14249.6
A44: Макс. CAC при окупаемости ≤ N мес | B44: =cm_month_b*payback_months_b -> 8977.248 | C44: =cm_month_b*payback_months_b -> 8977.248 | D44: =cm_month_b*payback_months_b -> 8977.248
A45: CAC в сценарии | B45: =sc_cac_b_P -> 4500 | C45: =sc_cac_b_R -> 3000 | D45: =sc_cac_b_O -> 2500
A46: LTV / CAC в сценарии | B46: =cm_month_b/sc_churn_P/sc_cac_b_P -> 5.5415111 | C46: =cm_month_b/sc_churn_R/sc_cac_b_R -> 11.083022 | D46: =cm_month_b/sc_churn_O/sc_cac_b_O -> 17.09952
A47: Окупаемость CAC, мес | B47: =sc_cac_b_P/cm_month_b -> 1.5038016 | C47: =sc_cac_b_R/cm_month_b -> 1.0025344 | D47: =sc_cac_b_O/cm_month_b -> 0.83544534
A49: Прежний прайс сайта vs рекомендуемый (2-комн., 1 санузел) | B49: Прежний: доля ФОТ как в модели | C49: Прежний: рыночная ставка клинера | D49: Рекомендуемый прайс
A50: Генеральная, ₽ | B50: =(cur_gen_base+cur_rooms*cur_gen_room+cur_baths*cur_gen_bath) -> 6000 | C50: =(cur_gen_base+cur_rooms*cur_gen_room+cur_baths*cur_gen_bath) -> 6000 | D50: =UA_area*UA_price_general_m2 -> 10800
A51: После ремонта, ₽ | B51: =(cur_post_base+cur_rooms*cur_post_room+cur_baths*cur_post_bath) -> 8600 | C51: =(cur_post_base+cur_rooms*cur_post_room+cur_baths*cur_post_bath) -> 8600 | D51: =UA_area*UA_price_repair_m2 -> 13800
A52: Норма времени: генеральная / после ремонта (движок), ч | B52: =(cur_gen_min+cur_post_min)/2/60 -> 5.875 | C52: =(cur_gen_min+cur_post_min)/2/60 -> 5.875 | D52: =UA_man_hours -> 14
A53: Средний чек A (с допчеком) | B53: =((cur_gen_base+cur_rooms*cur_gen_room+cur_baths*cur_gen_bath)*(1-UA_share_repair)+(cur_post_base+cur_rooms*cur_post_room+cur_baths*cur_post_bath)*UA_share_repair+UA_upsell) -> 8500 | C53: =((cur_gen_base+cur_rooms*cur_gen_room+cur_baths*cur_gen_bath)*(1-UA_share_repair)+(cur_post_base+cur_rooms*cur_post_room+cur_baths*cur_post_bath)*UA_share_repair+UA_upsell) -> 8500 | D53: =aov_a -> 13500
A54: Оплата клинеров A, ₽ | B54: =((cur_gen_base+cur_rooms*cur_gen_room+cur_baths*cur_gen_bath)*(1-UA_share_repair)+(cur_post_base+cur_rooms*cur_post_room+cur_baths*cur_post_bath)*UA_share_repair+UA_upsell)*UA_labor_share -> 3400 | C54: =labor_a -> 5400 | D54: =labor_a -> 5400
A55: … доля от чека | B55: =UA_labor_share -> 0.4 | C55: =labor_a/((cur_gen_base+cur_rooms*cur_gen_room+cur_baths*cur_gen_bath)*(1-UA_share_repair)+(cur_post_base+cur_rooms*cur_post_room+cur_baths*cur_post_bath)*UA_share_repair+UA_upsell) -> 0.63529412 | D55: =UA_labor_share -> 0.4
A56: … ставка клинера при трудоёмкости модели, ₽/чел-ч | B56: =((cur_gen_base+cur_rooms*cur_gen_room+cur_baths*cur_gen_bath)*(1-UA_share_repair)+(cur_post_base+cur_rooms*cur_post_room+cur_baths*cur_post_bath)*UA_share_repair+UA_upsell)*UA_labor_share/UA_man_hours -> 242.85714 | C56: =labor_a/UA_man_hours -> 385.71429 | D56: =labor_a/UA_man_hours -> 385.71429
A57: Маржинальный доход A до CAC | B57: =((cur_gen_base+cur_rooms*cur_gen_room+cur_baths*cur_gen_bath)*(1-UA_share_repair)+(cur_post_base+cur_rooms*cur_post_room+cur_baths*cur_post_bath)*UA_share_repair+UA_upsell)*(1-UA_labor_share-(acquiring+UA_quality_reserve+usn_rate))-(UA_chem+UA_amort+UA_logistics) -> 2692.5 | C57: =((cur_gen_base+cur_rooms*cur_gen_room+cur_baths*cur_gen_bath)*(1-UA_share_repair)+(cur_post_base+cur_rooms*cur_post_room+cur_baths*cur_post_bath)*UA_share_repair+UA_upsell)*(1-(acquiring+UA_quality_reserve+usn_rate))-labor_a-(UA_chem+UA_amort+UA_logistics) -> 692.5 | D57: =cm_a -> 5217.5
A58: … маржинальность A | B58: =(((cur_gen_base+cur_rooms*cur_gen_room+cur_baths*cur_gen_bath)*(1-UA_share_repair)+(cur_post_base+cur_rooms*cur_post_room+cur_baths*cur_post_bath)*UA_share_repair+UA_upsell)*(1-UA_labor_share-(acquiring+UA_quality_reserve+usn_rate))-(UA_chem+UA_amort+UA_logistics))/((cur_gen_base+cur_rooms*cur_gen_room+cur_baths*cur_gen_bath)*(1-UA_share_repair)+(cur_post_base+cur_rooms*cur_post_room+cur_baths*cur_post_bath)*UA_share_repair+UA_upsell) -> 0.31676471 | C58: =(((cur_gen_base+cur_rooms*cur_gen_room+cur_baths*cur_gen_bath)*(1-UA_share_repair)+(cur_post_base+cur_rooms*cur_post_room+cur_baths*cur_post_bath)*UA_share_repair+UA_upsell)*(1-(acquiring+UA_quality_reserve+usn_rate))-labor_a-(UA_chem+UA_amort+UA_logistics))/((cur_gen_base+cur_rooms*cur_gen_room+cur_baths*cur_gen_bath)*(1-UA_share_repair)+(cur_post_base+cur_rooms*cur_post_room+cur_baths*cur_post_bath)*UA_share_repair+UA_upsell) -> 0.081470588 | D58: =cm_a/aov_a -> 0.38648148
A59: Поддерживающая разово, ₽ | B59: =(cur_maint_base+cur_rooms*cur_maint_room+cur_baths*cur_maint_bath) -> 2750 | C59: =(cur_maint_base+cur_rooms*cur_maint_room+cur_baths*cur_maint_bath) -> 2750 | D59: =UB_price_single -> 3900
A60: Визит по подписке, ₽ | B60: =((cur_maint_base+cur_rooms*cur_maint_room+cur_baths*cur_maint_bath)*(1-UB_sub_discount)) -> 2420 | C60: =((cur_maint_base+cur_rooms*cur_maint_room+cur_baths*cur_maint_bath)*(1-UB_sub_discount)) -> 2420 | D60: =price_b -> 3432
A61: Ставка клинера на визите, ₽/ч | B61: =((cur_maint_base+cur_rooms*cur_maint_room+cur_baths*cur_maint_bath)*(1-UB_sub_discount))*UB_labor_share/UB_hours -> 311.14286 | C61: =labor_b/UB_hours -> 441.25714 | D61: =labor_b/UB_hours -> 441.25714
A62: Маржинальный доход на визит | B62: =((cur_maint_base+cur_rooms*cur_maint_room+cur_baths*cur_maint_bath)*(1-UB_sub_discount))*(1-UB_labor_share-(acquiring+UB_quality_reserve+usn_rate))-(UB_chem+UB_amort+UB_logistics) -> 603.2 | C62: =((cur_maint_base+cur_rooms*cur_maint_room+cur_baths*cur_maint_bath)*(1-UB_sub_discount))*(1-(acquiring+UB_quality_reserve+usn_rate))-labor_b-(UB_chem+UB_amort+UB_logistics) -> 147.8 | D62: =cm_b -> 1068.72
A63: Маржинальный доход с подписчика в месяц | B63: =(((cur_maint_base+cur_rooms*cur_maint_room+cur_baths*cur_maint_bath)*(1-UB_sub_discount))*(1-UB_labor_share-(acquiring+UB_quality_reserve+usn_rate))-(UB_chem+UB_amort+UB_logistics))*UB_visits_per_month -> 1688.96 | C63: =(((cur_maint_base+cur_rooms*cur_maint_room+cur_baths*cur_maint_bath)*(1-UB_sub_discount))*(1-(acquiring+UB_quality_reserve+usn_rate))-labor_b-(UB_chem+UB_amort+UB_logistics))*UB_visits_per_month -> 413.84 | D63: =cm_month_b -> 2992.416
A64: Трудоёмкость модели: генеральная ~12, после ремонта ~16 чел-ч; FAQ сайта: «2 специалиста на 4–6 часов» для генеральной 2-комн.
A66: Тип S — спецуслуги (химчистка мебели, окна) | B66: ₽ / значение | C66: % от чека | D66: Комментарий
A67: Средний чек | B67: =US_aov -> 4500 | C67: =IF(aov_s=0,0,B67/aov_s) -> 1
A68: Оплата мастера | B68: =aov_s*US_labor_share -> 1575 | C68: =IF(aov_s=0,0,B68/aov_s) -> 0.35
A69: Химия | B69: =US_chem -> 300 | C69: =IF(aov_s=0,0,B69/aov_s) -> 0.066666667
A70: Амортизация | B70: =US_amort -> 350 | C70: =IF(aov_s=0,0,B70/aov_s) -> 0.077777778
A71: Логистика | B71: =US_logistics -> 400 | C71: =IF(aov_s=0,0,B71/aov_s) -> 0.088888889
A72: Эквайринг / СБП | B72: =aov_s*acquiring -> 67.5 | C72: =IF(aov_s=0,0,B72/aov_s) -> 0.015
A73: Резерв качества | B73: =aov_s*US_quality_reserve -> 67.5 | C73: =IF(aov_s=0,0,B73/aov_s) -> 0.015
A74: Переменные затраты | B74: =SUM(B68:B73) -> 2760 | C74: =IF(aov_s=0,0,B74/aov_s) -> 0.61333333
A75: Валовая прибыль | B75: =aov_s-var_s -> 1740 | C75: =IF(aov_s=0,0,B75/aov_s) -> 0.38666667
A76: УСН | B76: =aov_s*usn_rate -> 270 | C76: =IF(aov_s=0,0,B76/aov_s) -> 0.06
A77: Маржинальный доход | B77: =B75-B76 -> 1470 | C77: =IF(aov_s=0,0,B77/aov_s) -> 0.32666667
A79: B2B — договор на обслуживание офиса, в месяц | B79: ₽ / значение | C79: % от чека | D79: Комментарий
A80: Сумма договора | B80: =b2b_value -> 55000 | C80: =IF(b2b_value=0,0,B80/b2b_value) -> 1
A81: Прямые затраты | B81: =b2b_value*b2b_direct_share -> 37400 | C81: =IF(b2b_value=0,0,B81/b2b_value) -> 0.68
A82: УСН | B82: =b2b_value*usn_rate -> 3300 | C82: =IF(b2b_value=0,0,B82/b2b_value) -> 0.06
A83: Маржинальный доход | B83: =b2b_value-b2b_direct-B82 -> 14300 | C83: =IF(b2b_value=0,0,B83/b2b_value) -> 0.26

Sheet ОПиУ_Пессимист
A1: ОПиУ и денежный поток — сценарий «Пессимистичный», ₽
A2: Показатель | B2: Итого 24 мес | C2: M1 ноя 26 | D2: M2 дек 26 | E2: M3 янв 27 | F2: M4 фев 27 | G2: M5 мар 27 | H2: M6 апр 27 | I2: M7 май 27 | J2: M8 июн 27 | K2: M9 июл 27 | L2: M10 авг 27 | M2: M11 сен 27 | N2: M12 окт 27 | O2: M13 ноя 27 | P2: M14 дек 27 | Q2: M15 янв 28 | R2: M16 фев 28 | S2: M17 мар 28 | T2: M18 апр 28 | U2: M19 май 28 | V2: M20 июн 28 | W2: M21 июл 28 | X2: M22 авг 28 | Y2: M23 сен 28 | Z2: M24 окт 28
A3: Месяц № | C3: 1 | D3: 2 | E3: 3 | F3: 4 | G3: 5 | H3: 6 | I3: 7 | J3: 8 | K3: 9 | L3: 10 | M3: 11 | N3: 12 | O3: 13 | P3: 14 | Q3: 15 | R3: 16 | S3: 17 | T3: 18 | U3: 19 | V3: 20 | W3: 21 | X3: 22 | Y3: 23 | Z3: 24
A4: Год | C4: =start_year+INT((start_month-1+C3-1)/12) -> 2026 | D4: =start_year+INT((start_month-1+D3-1)/12) -> 2026 | E4: =start_year+INT((start_month-1+E3-1)/12) -> 2027 | F4: =start_year+INT((start_month-1+F3-1)/12) -> 2027 | G4: =start_year+INT((start_month-1+G3-1)/12) -> 2027 | H4: =start_year+INT((start_month-1+H3-1)/12) -> 2027 | I4: =start_year+INT((start_month-1+I3-1)/12) -> 2027 | J4: =start_year+INT((start_month-1+J3-1)/12) -> 2027 | ... Z4: =start_year+INT((start_month-1+Z3-1)/12) -> 2028
A5: Календарный месяц | C5: =MOD(start_month-1+C3-1,12)+1 -> 11 | D5: =MOD(start_month-1+D3-1,12)+1 -> 12 | E5: =MOD(start_month-1+E3-1,12)+1 -> 1 | F5: =MOD(start_month-1+F3-1,12)+1 -> 2 | G5: =MOD(start_month-1+G3-1,12)+1 -> 3 | H5: =MOD(start_month-1+H3-1,12)+1 -> 4 | I5: =MOD(start_month-1+I3-1,12)+1 -> 5 | J5: =MOD(start_month-1+J3-1,12)+1 -> 6 | ... Z5: =MOD(start_month-1+Z3-1,12)+1 -> 10
A6: Индекс сезонности | C6: =INDEX(season_tbl,C5) -> 0.95 | D6: =INDEX(season_tbl,D5) -> 1.2 | E6: =INDEX(season_tbl,E5) -> 0.7 | F6: =INDEX(season_tbl,F5) -> 0.8 | G6: =INDEX(season_tbl,G5) -> 0.95 | H6: =INDEX(season_tbl,H5) -> 1.15 | I6: =INDEX(season_tbl,I5) -> 1.25 | J6: =INDEX(season_tbl,J5) -> 1.1 | ... Z6: =INDEX(season_tbl,Z5) -> 1
A8: ОБЪЁМЫ
A9: Заказы A до сезонности | C9: =IF(C3<=6,sc_a_start_P+(sc_a_m6_P-sc_a_start_P)*(C3-1)/5,sc_a_m6_P*(1+sc_a_growth_P)^(C3-6)) -> 8 | D9: =IF(D3<=6,sc_a_start_P+(sc_a_m6_P-sc_a_start_P)*(D3-1)/5,sc_a_m6_P*(1+sc_a_growth_P)^(D3-6)) -> 12 | E9: =IF(E3<=6,sc_a_start_P+(sc_a_m6_P-sc_a_start_P)*(E3-1)/5,sc_a_m6_P*(1+sc_a_growth_P)^(E3-6)) -> 16 | F9: =IF(F3<=6,sc_a_start_P+(sc_a_m6_P-sc_a_start_P)*(F3-1)/5,sc_a_m6_P*(1+sc_a_growth_P)^(F3-6)) -> 20 | G9: =IF(G3<=6,sc_a_start_P+(sc_a_m6_P-sc_a_start_P)*(G3-1)/5,sc_a_m6_P*(1+sc_a_growth_P)^(G3-6)) -> 24 | H9: =IF(H3<=6,sc_a_start_P+(sc_a_m6_P-sc_a_start_P)*(H3-1)/5,sc_a_m6_P*(1+sc_a_growth_P)^(H3-6)) -> 28 | I9: =IF(I3<=6,sc_a_start_P+(sc_a_m6_P-sc_a_start_P)*(I3-1)/5,sc_a_m6_P*(1+sc_a_growth_P)^(I3-6)) -> 28.56 | J9: =IF(J3<=6,sc_a_start_P+(sc_a_m6_P-sc_a_start_P)*(J3-1)/5,sc_a_m6_P*(1+sc_a_growth_P)^(J3-6)) -> 29.1312 | ... Z9: =IF(Z3<=6,sc_a_start_P+(sc_a_m6_P-sc_a_start_P)*(Z3-1)/5,sc_a_m6_P*(1+sc_a_growth_P)^(Z3-6)) -> 39.990895
A10: Заказы A (генеральная / после ремонта) | B10: =SUM(C10:Z10) -> 733.92202 | C10: =MIN(sc_a_cap_P,C9*C6) -> 7.6 | D10: =MIN(sc_a_cap_P,D9*D6) -> 14.4 | E10: =MIN(sc_a_cap_P,E9*E6) -> 11.2 | F10: =MIN(sc_a_cap_P,F9*F6) -> 16 | G10: =MIN(sc_a_cap_P,G9*G6) -> 22.8 | H10: =MIN(sc_a_cap_P,H9*H6) -> 32.2 | I10: =MIN(sc_a_cap_P,I9*I6) -> 35.7 | J10: =MIN(sc_a_cap_P,J9*J6) -> 32.04432 | ... Z10: =MIN(sc_a_cap_P,Z9*Z6) -> 39.990895
A11: Новые подписчики B | B11: =SUM(C11:Z11) -> 165.67627 | C11: =IF(C3<=6,sc_s_start_P+(sc_s_m6_P-sc_s_start_P)*(C3-1)/5,sc_s_m6_P*(1+sc_s_growth_P)^(C3-6)) -> 2 | D11: =IF(D3<=6,sc_s_start_P+(sc_s_m6_P-sc_s_start_P)*(D3-1)/5,sc_s_m6_P*(1+sc_s_growth_P)^(D3-6)) -> 3 | E11: =IF(E3<=6,sc_s_start_P+(sc_s_m6_P-sc_s_start_P)*(E3-1)/5,sc_s_m6_P*(1+sc_s_growth_P)^(E3-6)) -> 4 | F11: =IF(F3<=6,sc_s_start_P+(sc_s_m6_P-sc_s_start_P)*(F3-1)/5,sc_s_m6_P*(1+sc_s_growth_P)^(F3-6)) -> 5 | G11: =IF(G3<=6,sc_s_start_P+(sc_s_m6_P-sc_s_start_P)*(G3-1)/5,sc_s_m6_P*(1+sc_s_growth_P)^(G3-6)) -> 6 | H11: =IF(H3<=6,sc_s_start_P+(sc_s_m6_P-sc_s_start_P)*(H3-1)/5,sc_s_m6_P*(1+sc_s_growth_P)^(H3-6)) -> 7 | I11: =IF(I3<=6,sc_s_start_P+(sc_s_m6_P-sc_s_start_P)*(I3-1)/5,sc_s_m6_P*(1+sc_s_growth_P)^(I3-6)) -> 7.07 | J11: =IF(J3<=6,sc_s_start_P+(sc_s_m6_P-sc_s_start_P)*(J3-1)/5,sc_s_m6_P*(1+sc_s_growth_P)^(J3-6)) -> 7.1407 | ... Z11: =IF(Z3<=6,sc_s_start_P+(sc_s_m6_P-sc_s_start_P)*(Z3-1)/5,sc_s_m6_P*(1+sc_s_growth_P)^(Z3-6)) -> 8.3730323
A12: Активные подписчики B | C12: =C11 -> 2 | D12: =C12*(1-sc_churn_P)+D11 -> 4.76 | E12: =D12*(1-sc_churn_P)+E11 -> 8.1888 | F12: =E12*(1-sc_churn_P)+F11 -> 12.206144 | G12: =F12*(1-sc_churn_P)+G11 -> 16.741407 | H12: =G12*(1-sc_churn_P)+H11 -> 21.732438 | I12: =H12*(1-sc_churn_P)+I11 -> 26.194545 | J12: =I12*(1-sc_churn_P)+J11 -> 30.1919 | K12: =J12*(1-sc_churn_P)+K11 -> 33.780979 | ... Z12: =Y12*(1-sc_churn_P)+Z11 -> 61.781625
A13: Визиты B | B13: =SUM(C13:Z13) -> 2597.1968 | C13: =C12*UB_visits_per_month -> 5.6 | D13: =D12*UB_visits_per_month -> 13.328 | E13: =E12*UB_visits_per_month -> 22.92864 | F13: =F12*UB_visits_per_month -> 34.177203 | G13: =G12*UB_visits_per_month -> 46.875939 | H13: =H12*UB_visits_per_month -> 60.850826 | I13: =I12*UB_visits_per_month -> 73.344727 | J13: =J12*UB_visits_per_month -> 84.53732 | ... Z13: =Z12*UB_visits_per_month -> 172.98855
A14: Заказы спецуслуг S | B14: =SUM(C14:Z14) -> 220.17661 | C14: =C10*sc_spec_ratio_P -> 2.28 | D14: =D10*sc_spec_ratio_P -> 4.32 | E14: =E10*sc_spec_ratio_P -> 3.36 | F14: =F10*sc_spec_ratio_P -> 4.8 | G14: =G10*sc_spec_ratio_P -> 6.84 | H14: =H10*sc_spec_ratio_P -> 9.66 | I14: =I10*sc_spec_ratio_P -> 10.71 | J14: =J10*sc_spec_ratio_P -> 9.613296 | ... Z14: =Z10*sc_spec_ratio_P -> 11.997268
A15: Действующие B2B-договоры | C15: =IF(C3>=sc_b2b_start_P,MIN(sc_b2b_max_P,INT((C3-sc_b2b_start_P)/sc_b2b_step_P)+1),0) -> 0 | D15: =IF(D3>=sc_b2b_start_P,MIN(sc_b2b_max_P,INT((D3-sc_b2b_start_P)/sc_b2b_step_P)+1),0) -> 0 | E15: =IF(E3>=sc_b2b_start_P,MIN(sc_b2b_max_P,INT((E3-sc_b2b_start_P)/sc_b2b_step_P)+1),0) -> 0 | F15: =IF(F3>=sc_b2b_start_P,MIN(sc_b2b_max_P,INT((F3-sc_b2b_start_P)/sc_b2b_step_P)+1),0) -> 0 | G15: =IF(G3>=sc_b2b_start_P,MIN(sc_b2b_max_P,INT((G3-sc_b2b_start_P)/sc_b2b_step_P)+1),0) -> 0 | H15: =IF(H3>=sc_b2b_start_P,MIN(sc_b2b_max_P,INT((H3-sc_b2b_start_P)/sc_b2b_step_P)+1),0) -> 0 | I15: =IF(I3>=sc_b2b_start_P,MIN(sc_b2b_max_P,INT((I3-sc_b2b_start_P)/sc_b2b_step_P)+1),0) -> 1 | J15: =IF(J3>=sc_b2b_start_P,MIN(sc_b2b_max_P,INT((J3-sc_b2b_start_P)/sc_b2b_step_P)+1),0) -> 1 | ... Z15: =IF(Z3>=sc_b2b_start_P,MIN(sc_b2b_max_P,INT((Z3-sc_b2b_start_P)/sc_b2b_step_P)+1),0) -> 2
A16: Потребность в клинерах, FTE | C16: =(C10*UA_man_hours+C13*UB_hours+C14*US_man_hours)/hours_per_fte+C15*b2b_fte -> 0.8856 | D16: =(D10*UA_man_hours+D13*UB_hours+D14*US_man_hours)/hours_per_fte+D15*b2b_fte -> 1.7413867 | E16: =(E10*UA_man_hours+E13*UB_hours+E14*US_man_hours)/hours_per_fte+E15*b2b_fte -> 1.6475349 | F16: =(F10*UA_man_hours+F13*UB_hours+F14*US_man_hours)/hours_per_fte+F15*b2b_fte -> 2.3868014 | G16: =(G10*UA_man_hours+G13*UB_hours+G14*US_man_hours)/hours_per_fte+G15*b2b_fte -> 3.3585719 | H16: =(H10*UA_man_hours+H13*UB_hours+H14*US_man_hours)/hours_per_fte+H15*b2b_fte -> 4.6183859 | I16: =(I10*UA_man_hours+I13*UB_hours+I14*US_man_hours)/hours_per_fte+I15*b2b_fte -> 6.257577 | J16: =(J10*UA_man_hours+J13*UB_hours+J14*US_man_hours)/hours_per_fte+J15*b2b_fte -> 6.1556066 | ... Z16: =(Z10*UA_man_hours+Z13*UB_hours+Z14*US_man_hours)/hours_per_fte+Z15*b2b_fte -> 10.008828
A18: ОПиУ
A19: Выручка A | B19: =SUM(C19:Z19) -> 9907947.3 | C19: =C10*aov_a -> 102600 | D19: =D10*aov_a -> 194400 | E19: =E10*aov_a -> 151200 | F19: =F10*aov_a -> 216000 | G19: =G10*aov_a -> 307800 | H19: =H10*aov_a -> 434700 | I19: =I10*aov_a -> 481950 | J19: =J10*aov_a -> 432598.32 | ... Z19: =Z10*aov_a -> 539877.08
A20: Выручка B (подписка) | B20: =SUM(C20:Z20) -> 8913579.5 | C20: =C13*price_b -> 19219.2 | D20: =D13*price_b -> 45741.696 | E20: =E13*price_b -> 78691.092 | F20: =F13*price_b -> 117296.16 | G20: =G13*price_b -> 160878.22 | H20: =H13*price_b -> 208840.04 | I20: =I13*price_b -> 251719.1 | J20: =J13*price_b -> 290132.08 | ... Z20: =Z13*price_b -> 593696.7
A21: Выручка S (спецуслуги) | B21: =SUM(C21:Z21) -> 990794.73 | C21: =C14*aov_s -> 10260 | D21: =D14*aov_s -> 19440 | E21: =E14*aov_s -> 15120 | F21: =F14*aov_s -> 21600 | G21: =G14*aov_s -> 30780 | H21: =H14*aov_s -> 43470 | I21: =I14*aov_s -> 48195 | J21: =J14*aov_s -> 43259.832 | ... Z21: =Z14*aov_s -> 53987.708
A22: Выручка B2B | B22: =SUM(C22:Z22) -> 1650000 | C22: =C15*b2b_value -> 0 | D22: =D15*b2b_value -> 0 | E22: =E15*b2b_value -> 0 | F22: =F15*b2b_value -> 0 | G22: =G15*b2b_value -> 0 | H22: =H15*b2b_value -> 0 | I22: =I15*b2b_value -> 55000 | J22: =J15*b2b_value -> 55000 | ... Z22: =Z15*b2b_value -> 110000
A23: ВЫРУЧКА | B23: =SUM(C23:Z23) -> 21462321 | C23: =SUM(C19:C22) -> 132079.2 | D23: =SUM(D19:D22) -> 259581.7 | E23: =SUM(E19:E22) -> 245011.09 | F23: =SUM(F19:F22) -> 354896.16 | G23: =SUM(G19:G22) -> 499458.22 | H23: =SUM(H19:H22) -> 687010.04 | I23: =SUM(I19:I22) -> 836864.1 | J23: =SUM(J19:J22) -> 820990.23 | ... Z23: =SUM(Z19:Z22) -> 1297561.5
A24: Переменные затраты (ФОТ клинеров, химия, логистика, эквайринг, резерв) | B24: =SUM(C24:Z24) -> 12817008 | C24: =C10*var_a+C13*var_b+C14*var_s+C15*b2b_direct -> 75165.016 | D24: =D10*var_a+D13*var_b+D14*var_s+D15*b2b_direct -> 148280.49 | E24: =E10*var_a+E13*var_b+E14*var_s+E15*b2b_direct -> 142430.93 | F24: =F10*var_a+F13*var_b+F14*var_s+F15*b2b_direct -> 206540.53 | G24: =G10*var_a+G13*var_b+G14*var_s+G15*b2b_direct -> 290379.68 | H24: =H10*var_a+H13*var_b+H14*var_s+H15*b2b_direct -> 398553.24 | I24: =I10*var_a+I13*var_b+I14*var_s+I15*b2b_direct -> 491958.83 | J24: =J10*var_a+J13*var_b+J14*var_s+J15*b2b_direct -> 485761.31 | ... Z24: =Z10*var_a+Z13*var_b+Z14*var_s+Z15*b2b_direct -> 779943
A25: Валовая прибыль | B25: =SUM(C25:Z25) -> 8645313.2 | C25: =C23-C24 -> 56914.184 | D25: =D23-D24 -> 111301.2 | E25: =E23-E24 -> 102580.16 | F25: =F23-F24 -> 148355.63 | G25: =G23-G24 -> 209078.55 | H25: =H23-H24 -> 288456.8 | I25: =I23-I24 -> 344905.27 | J25: =J23-J24 -> 335228.92 | ... Z25: =Z23-Z24 -> 517618.49
A26: Маркетинг (CAC: партнёрам, продвижение, скидка 1-го визита) | B26: =SUM(C26:Z26) -> 2051924.4 | C26: =C10*sc_cac_a_P+C11*sc_cac_b_P+C14*sc_cac_s_P -> 22528 | D26: =D10*sc_cac_a_P+D11*sc_cac_b_P+D14*sc_cac_s_P -> 39132 | E26: =E10*sc_cac_a_P+E11*sc_cac_b_P+E14*sc_cac_s_P -> 37936 | F26: =F10*sc_cac_a_P+F11*sc_cac_b_P+F14*sc_cac_s_P -> 50980 | G26: =G10*sc_cac_a_P+G11*sc_cac_b_P+G14*sc_cac_s_P -> 67584 | H26: =H10*sc_cac_a_P+H11*sc_cac_b_P+H14*sc_cac_s_P -> 88816 | I26: =I10*sc_cac_a_P+I11*sc_cac_b_P+I14*sc_cac_s_P -> 95361 | J26: =J10*sc_cac_a_P+J11*sc_cac_b_P+J14*sc_cac_s_P -> 89172.04 | ... Z26: =Z10*sc_cac_a_P+Z11*sc_cac_b_P+Z14*sc_cac_s_P -> 108862.44
A27: Постоянные расходы (FIX) | B27: =SUM(C27:Z27) -> 4310400 | C27: =fix_base+fix_step_cost*INT(C23/fix_rev_step) -> 179600 | D27: =fix_base+fix_step_cost*INT(D23/fix_rev_step) -> 179600 | E27: =fix_base+fix_step_cost*INT(E23/fix_rev_step) -> 179600 | F27: =fix_base+fix_step_cost*INT(F23/fix_rev_step) -> 179600 | G27: =fix_base+fix_step_cost*INT(G23/fix_rev_step) -> 179600 | H27: =fix_base+fix_step_cost*INT(H23/fix_rev_step) -> 179600 | I27: =fix_base+fix_step_cost*INT(I23/fix_rev_step) -> 179600 | J27: =fix_base+fix_step_cost*INT(J23/fix_rev_step) -> 179600 | ... Z27: =fix_base+fix_step_cost*INT(Z23/fix_rev_step) -> 179600
A28: НДС применяется (1 = да) | C28: =IF(OR(SUMIFS($C$23:$Z$23,$C$4:$Z$4,C4-1)>vat_threshold,SUMIFS($C$23:$Z$23,$C$4:$Z$4,C4,$C$3:$Z$3,"<"&C3)>vat_threshold),1,0) -> 0 | D28: =IF(OR(SUMIFS($C$23:$Z$23,$C$4:$Z$4,D4-1)>vat_threshold,SUMIFS($C$23:$Z$23,$C$4:$Z$4,D4,$C$3:$Z$3,"<"&D3)>vat_threshold),1,0) -> 0 | E28: =IF(OR(SUMIFS($C$23:$Z$23,$C$4:$Z$4,E4-1)>vat_threshold,SUMIFS($C$23:$Z$23,$C$4:$Z$4,E4,$C$3:$Z$3,"<"&E3)>vat_threshold),1,0) -> 0 | F28: =IF(OR(SUMIFS($C$23:$Z$23,$C$4:$Z$4,F4-1)>vat_threshold,SUMIFS($C$23:$Z$23,$C$4:$Z$4,F4,$C$3:$Z$3,"<"&F3)>vat_threshold),1,0) -> 0 | G28: =IF(OR(SUMIFS($C$23:$Z$23,$C$4:$Z$4,G4-1)>vat_threshold,SUMIFS($C$23:$Z$23,$C$4:$Z$4,G4,$C$3:$Z$3,"<"&G3)>vat_threshold),1,0) -> 0 | H28: =IF(OR(SUMIFS($C$23:$Z$23,$C$4:$Z$4,H4-1)>vat_threshold,SUMIFS($C$23:$Z$23,$C$4:$Z$4,H4,$C$3:$Z$3,"<"&H3)>vat_threshold),1,0) -> 0 | I28: =IF(OR(SUMIFS($C$23:$Z$23,$C$4:$Z$4,I4-1)>vat_threshold,SUMIFS($C$23:$Z$23,$C$4:$Z$4,I4,$C$3:$Z$3,"<"&I3)>vat_threshold),1,0) -> 0 | J28: =IF(OR(SUMIFS($C$23:$Z$23,$C$4:$Z$4,J4-1)>vat_threshold,SUMIFS($C$23:$Z$23,$C$4:$Z$4,J4,$C$3:$Z$3,"<"&J3)>vat_threshold),1,0) -> 0 | ... Z28: =IF(OR(SUMIFS($C$23:$Z$23,$C$4:$Z$4,Z4-1)>vat_threshold,SUMIFS($C$23:$Z$23,$C$4:$Z$4,Z4,$C$3:$Z$3,"<"&Z3)>vat_threshold),1,0) -> 0
A29: НДС (выделяется из цены) | B29: =SUM(C29:Z29) -> 0 | C29: =C23*vat_rate/(1+vat_rate)*C28 -> 0 | D29: =D23*vat_rate/(1+vat_rate)*D28 -> 0 | E29: =E23*vat_rate/(1+vat_rate)*E28 -> 0 | F29: =F23*vat_rate/(1+vat_rate)*F28 -> 0 | G29: =G23*vat_rate/(1+vat_rate)*G28 -> 0 | H29: =H23*vat_rate/(1+vat_rate)*H28 -> 0 | I29: =I23*vat_rate/(1+vat_rate)*I28 -> 0 | J29: =J23*vat_rate/(1+vat_rate)*J28 -> 0 | ... Z29: =Z23*vat_rate/(1+vat_rate)*Z28 -> 0
A30: УСН | B30: =SUM(C30:Z30) -> 1287739.3 | C30: =(C23-C29)*usn_rate -> 7924.752 | D30: =(D23-D29)*usn_rate -> 15574.902 | E30: =(E23-E29)*usn_rate -> 14700.666 | F30: =(F23-F29)*usn_rate -> 21293.77 | G30: =(G23-G29)*usn_rate -> 29967.493 | H30: =(H23-H29)*usn_rate -> 41220.602 | I30: =(I23-I29)*usn_rate -> 50211.846 | J30: =(J23-J29)*usn_rate -> 49259.414 | ... Z30: =(Z23-Z29)*usn_rate -> 77853.69
A31: ОПЕРАЦИОННАЯ ПРИБЫЛЬ | B31: =SUM(C31:Z31) -> 995249.55 | C31: =C23-C29-C24-C26-C27-C30 -> -153138.57 | D31: =D23-D29-D24-D26-D27-D30 -> -123005.7 | E31: =E23-E29-E24-E26-E27-E30 -> -129656.5 | F31: =F23-F29-F24-F26-F27-F30 -> -103518.14 | G31: =G23-G29-G24-G26-G27-G30 -> -68072.947 | H31: =H23-H29-H24-H26-H27-H30 -> -21179.805 | I31: =I23-I29-I24-I26-I27-I30 -> 19732.427 | J31: =J23-J29-J24-J26-J27-J30 -> 17197.47 | ... Z31: =Z23-Z29-Z24-Z26-Z27-Z30 -> 151302.36
A32: Рентабельность по операционной прибыли | B32: =IF(B23=0,0,B31/B23) -> 0.046371943 | C32: =IF(C23=0,0,C31/C23) -> -1.159445 | D32: =IF(D23=0,0,D31/D23) -> -0.47386122 | E32: =IF(E23=0,0,E31/E23) -> -0.52918626 | F32: =IF(F23=0,0,F31/F23) -> -0.29168571 | G32: =IF(G23=0,0,G31/G23) -> -0.13629358 | H32: =IF(H23=0,0,H31/H23) -> -0.03082896 | I32: =IF(I23=0,0,I31/I23) -> 0.02357901 | ... Z32: =IF(Z23=0,0,Z31/Z23) -> 0.11660516
A34: ДЕНЕЖНЫЙ ПОТОК
A35: CAPEX 2-го этапа | B35: =SUM(C35:Z35) -> 335000 | C35: =IF(C3=sc_capex2_month_P,capex2_total,0) -> 0 | D35: =IF(D3=sc_capex2_month_P,capex2_total,0) -> 0 | E35: =IF(E3=sc_capex2_month_P,capex2_total,0) -> 0 | F35: =IF(F3=sc_capex2_month_P,capex2_total,0) -> 0 | G35: =IF(G3=sc_capex2_month_P,capex2_total,0) -> 0 | H35: =IF(H3=sc_capex2_month_P,capex2_total,0) -> 0 | I35: =IF(I3=sc_capex2_month_P,capex2_total,0) -> 0 | J35: =IF(J3=sc_capex2_month_P,capex2_total,0) -> 0 | ... Z35: =IF(Z3=sc_capex2_month_P,capex2_total,0) -> 0
A36: Денежный поток месяца | B36: =SUM(C36:Z36) -> 660249.55 | C36: =C31-C35 -> -153138.57 | D36: =D31-D35 -> -123005.7 | E36: =E31-E35 -> -129656.5 | F36: =F31-F35 -> -103518.14 | G36: =G31-G35 -> -68072.947 | H36: =H31-H35 -> -21179.805 | I36: =I31-I35 -> 19732.427 | J36: =J31-J35 -> 17197.47 | ... Z36: =Z31-Z35 -> 151302.36
A37: Накопленный ДП без стартовых вложений | C37: =C36 -> -153138.57 | D37: =C37+D36 -> -276144.27 | E37: =D37+E36 -> -405800.77 | F37: =E37+F36 -> -509318.91 | G37: =F37+G36 -> -577391.86 | H37: =G37+H36 -> -598571.66 | I37: =H37+I36 -> -578839.24 | J37: =I37+J36 -> -561641.77 | K37: =J37+K36 -> -554588.95 | ... Z37: =Y37+Z36 -> 660249.55
A38: Накопленный ДП с учётом CAPEX и предзапуска (M0) | C38: =-(capex_base+prelaunch_total)+C36 -> -727138.57 | D38: =C38+D36 -> -850144.27 | E38: =D38+E36 -> -979800.77 | F38: =E38+F36 -> -1083318.9 | G38: =F38+G36 -> -1151391.9 | H38: =G38+H36 -> -1172571.7 | I38: =H38+I36 -> -1152839.2 | J38: =I38+J36 -> -1135641.8 | K38: =J38+K36 -> -1128588.9 | ... Z38: =Y38+Z36 -> 86249.546
A39: Служебная: месяц, после которого нет убыточных месяцев | C39: =IF(COUNTIF(C31:$Z$31,"<0")=0,C3,"") | D39: =IF(COUNTIF(D31:$Z$31,"<0")=0,D3,"") | E39: =IF(COUNTIF(E31:$Z$31,"<0")=0,E3,"") | F39: =IF(COUNTIF(F31:$Z$31,"<0")=0,F3,"") | G39: =IF(COUNTIF(G31:$Z$31,"<0")=0,G3,"") | H39: =IF(COUNTIF(H31:$Z$31,"<0")=0,H3,"") | I39: =IF(COUNTIF(I31:$Z$31,"<0")=0,I3,"") -> 7 | J39: =IF(COUNTIF(J31:$Z$31,"<0")=0,J3,"") -> 8 | ... Z39: =IF(COUNTIF(Z31:$Z$31,"<0")=0,Z3,"") -> 24

Sheet ОПиУ_Реалист
A1: ОПиУ и денежный поток — сценарий «Реалистичный», ₽
A2: Показатель | B2: Итого 24 мес | C2: M1 ноя 26 | D2: M2 дек 26 | E2: M3 янв 27 | F2: M4 фев 27 | G2: M5 мар 27 | H2: M6 апр 27 | I2: M7 май 27 | J2: M8 июн 27 | K2: M9 июл 27 | L2: M10 авг 27 | M2: M11 сен 27 | N2: M12 окт 27 | O2: M13 ноя 27 | P2: M14 дек 27 | Q2: M15 янв 28 | R2: M16 фев 28 | S2: M17 мар 28 | T2: M18 апр 28 | U2: M19 май 28 | V2: M20 июн 28 | W2: M21 июл 28 | X2: M22 авг 28 | Y2: M23 сен 28 | Z2: M24 окт 28
A3: Месяц № | C3: 1 | D3: 2 | E3: 3 | F3: 4 | G3: 5 | H3: 6 | I3: 7 | J3: 8 | K3: 9 | L3: 10 | M3: 11 | N3: 12 | O3: 13 | P3: 14 | Q3: 15 | R3: 16 | S3: 17 | T3: 18 | U3: 19 | V3: 20 | W3: 21 | X3: 22 | Y3: 23 | Z3: 24
A4: Год | C4: =start_year+INT((start_month-1+C3-1)/12) -> 2026 | D4: =start_year+INT((start_month-1+D3-1)/12) -> 2026 | E4: =start_year+INT((start_month-1+E3-1)/12) -> 2027 | F4: =start_year+INT((start_month-1+F3-1)/12) -> 2027 | G4: =start_year+INT((start_month-1+G3-1)/12) -> 2027 | H4: =start_year+INT((start_month-1+H3-1)/12) -> 2027 | I4: =start_year+INT((start_month-1+I3-1)/12) -> 2027 | J4: =start_year+INT((start_month-1+J3-1)/12) -> 2027 | ... Z4: =start_year+INT((start_month-1+Z3-1)/12) -> 2028
A5: Календарный месяц | C5: =MOD(start_month-1+C3-1,12)+1 -> 11 | D5: =MOD(start_month-1+D3-1,12)+1 -> 12 | E5: =MOD(start_month-1+E3-1,12)+1 -> 1 | F5: =MOD(start_month-1+F3-1,12)+1 -> 2 | G5: =MOD(start_month-1+G3-1,12)+1 -> 3 | H5: =MOD(start_month-1+H3-1,12)+1 -> 4 | I5: =MOD(start_month-1+I3-1,12)+1 -> 5 | J5: =MOD(start_month-1+J3-1,12)+1 -> 6 | ... Z5: =MOD(start_month-1+Z3-1,12)+1 -> 10
A6: Индекс сезонности | C6: =INDEX(season_tbl,C5) -> 0.95 | D6: =INDEX(season_tbl,D5) -> 1.2 | E6: =INDEX(season_tbl,E5) -> 0.7 | F6: =INDEX(season_tbl,F5) -> 0.8 | G6: =INDEX(season_tbl,G5) -> 0.95 | H6: =INDEX(season_tbl,H5) -> 1.15 | I6: =INDEX(season_tbl,I5) -> 1.25 | J6: =INDEX(season_tbl,J5) -> 1.1 | ... Z6: =INDEX(season_tbl,Z5) -> 1
A8: ОБЪЁМЫ
A9: Заказы A до сезонности | C9: =IF(C3<=6,sc_a_start_R+(sc_a_m6_R-sc_a_start_R)*(C3-1)/5,sc_a_m6_R*(1+sc_a_growth_R)^(C3-6)) -> 12 | D9: =IF(D3<=6,sc_a_start_R+(sc_a_m6_R-sc_a_start_R)*(D3-1)/5,sc_a_m6_R*(1+sc_a_growth_R)^(D3-6)) -> 18.6 | E9: =IF(E3<=6,sc_a_start_R+(sc_a_m6_R-sc_a_start_R)*(E3-1)/5,sc_a_m6_R*(1+sc_a_growth_R)^(E3-6)) -> 25.2 | F9: =IF(F3<=6,sc_a_start_R+(sc_a_m6_R-sc_a_start_R)*(F3-1)/5,sc_a_m6_R*(1+sc_a_growth_R)^(F3-6)) -> 31.8 | G9: =IF(G3<=6,sc_a_start_R+(sc_a_m6_R-sc_a_start_R)*(G3-1)/5,sc_a_m6_R*(1+sc_a_growth_R)^(G3-6)) -> 38.4 | H9: =IF(H3<=6,sc_a_start_R+(sc_a_m6_R-sc_a_start_R)*(H3-1)/5,sc_a_m6_R*(1+sc_a_growth_R)^(H3-6)) -> 45 | I9: =IF(I3<=6,sc_a_start_R+(sc_a_m6_R-sc_a_start_R)*(I3-1)/5,sc_a_m6_R*(1+sc_a_growth_R)^(I3-6)) -> 46.8 | J9: =IF(J3<=6,sc_a_start_R+(sc_a_m6_R-sc_a_start_R)*(J3-1)/5,sc_a_m6_R*(1+sc_a_growth_R)^(J3-6)) -> 48.672 | ... Z9: =IF(Z3<=6,sc_a_start_R+(sc_a_m6_R-sc_a_start_R)*(Z3-1)/5,sc_a_m6_R*(1+sc_a_growth_R)^(Z3-6)) -> 91.161743
A10: Заказы A (генеральная / после ремонта) | B10: =SUM(C10:Z10) -> 1400.4105 | C10: =MIN(sc_a_cap_R,C9*C6) -> 11.4 | D10: =MIN(sc_a_cap_R,D9*D6) -> 22.32 | E10: =MIN(sc_a_cap_R,E9*E6) -> 17.64 | F10: =MIN(sc_a_cap_R,F9*F6) -> 25.44 | G10: =MIN(sc_a_cap_R,G9*G6) -> 36.48 | H10: =MIN(sc_a_cap_R,H9*H6) -> 51.75 | I10: =MIN(sc_a_cap_R,I9*I6) -> 58.5 | J10: =MIN(sc_a_cap_R,J9*J6) -> 53.5392 | ... Z10: =MIN(sc_a_cap_R,Z9*Z6) -> 91.161743
A11: Новые подписчики B | B11: =SUM(C11:Z11) -> 391.63616 | C11: =IF(C3<=6,sc_s_start_R+(sc_s_m6_R-sc_s_start_R)*(C3-1)/5,sc_s_m6_R*(1+sc_s_growth_R)^(C3-6)) -> 4 | D11: =IF(D3<=6,sc_s_start_R+(sc_s_m6_R-sc_s_start_R)*(D3-1)/5,sc_s_m6_R*(1+sc_s_growth_R)^(D3-6)) -> 6 | E11: =IF(E3<=6,sc_s_start_R+(sc_s_m6_R-sc_s_start_R)*(E3-1)/5,sc_s_m6_R*(1+sc_s_growth_R)^(E3-6)) -> 8 | F11: =IF(F3<=6,sc_s_start_R+(sc_s_m6_R-sc_s_start_R)*(F3-1)/5,sc_s_m6_R*(1+sc_s_growth_R)^(F3-6)) -> 10 | G11: =IF(G3<=6,sc_s_start_R+(sc_s_m6_R-sc_s_start_R)*(G3-1)/5,sc_s_m6_R*(1+sc_s_growth_R)^(G3-6)) -> 12 | H11: =IF(H3<=6,sc_s_start_R+(sc_s_m6_R-sc_s_start_R)*(H3-1)/5,sc_s_m6_R*(1+sc_s_growth_R)^(H3-6)) -> 14 | I11: =IF(I3<=6,sc_s_start_R+(sc_s_m6_R-sc_s_start_R)*(I3-1)/5,sc_s_m6_R*(1+sc_s_growth_R)^(I3-6)) -> 14.42 | J11: =IF(J3<=6,sc_s_start_R+(sc_s_m6_R-sc_s_start_R)*(J3-1)/5,sc_s_m6_R*(1+sc_s_growth_R)^(J3-6)) -> 14.8526 | ... Z11: =IF(Z3<=6,sc_s_start_R+(sc_s_m6_R-sc_s_start_R)*(Z3-1)/5,sc_s_m6_R*(1+sc_s_growth_R)^(Z3-6)) -> 23.834063
A12: Активные подписчики B | C12: =C11 -> 4 | D12: =C12*(1-sc_churn_R)+D11 -> 9.64 | E12: =D12*(1-sc_churn_R)+E11 -> 16.7724 | F12: =E12*(1-sc_churn_R)+F11 -> 25.262884 | G12: =F12*(1-sc_churn_R)+G11 -> 34.989224 | H12: =G12*(1-sc_churn_R)+H11 -> 45.840194 | I12: =H12*(1-sc_churn_R)+I11 -> 56.134577 | J12: =I12*(1-sc_churn_R)+J11 -> 65.935065 | K12: =J12*(1-sc_churn_R)+K11 -> 75.299087 | ... Z12: =Y12*(1-sc_churn_R)+Z11 -> 190.96475
A13: Визиты B | B13: =SUM(C13:Z13) -> 6777.8117 | C13: =C12*UB_visits_per_month -> 11.2 | D13: =D12*UB_visits_per_month -> 26.992 | E13: =E12*UB_visits_per_month -> 46.96272 | F13: =F12*UB_visits_per_month -> 70.736075 | G13: =G12*UB_visits_per_month -> 97.969828 | H13: =H12*UB_visits_per_month -> 128.35254 | I13: =I12*UB_visits_per_month -> 157.17681 | J13: =J12*UB_visits_per_month -> 184.61818 | ... Z13: =Z12*UB_visits_per_month -> 534.7013
A14: Заказы спецуслуг S | B14: =SUM(C14:Z14) -> 630.1847 | C14: =C10*sc_spec_ratio_R -> 5.13 | D14: =D10*sc_spec_ratio_R -> 10.044 | E14: =E10*sc_spec_ratio_R -> 7.938 | F14: =F10*sc_spec_ratio_R -> 11.448 | G14: =G10*sc_spec_ratio_R -> 16.416 | H14: =H10*sc_spec_ratio_R -> 23.2875 | I14: =I10*sc_spec_ratio_R -> 26.325 | J14: =J10*sc_spec_ratio_R -> 24.09264 | ... Z14: =Z10*sc_spec_ratio_R -> 41.022784
A15: Действующие B2B-договоры | C15: =IF(C3>=sc_b2b_start_R,MIN(sc_b2b_max_R,INT((C3-sc_b2b_start_R)/sc_b2b_step_R)+1),0) -> 0 | D15: =IF(D3>=sc_b2b_start_R,MIN(sc_b2b_max_R,INT((D3-sc_b2b_start_R)/sc_b2b_step_R)+1),0) -> 0 | E15: =IF(E3>=sc_b2b_start_R,MIN(sc_b2b_max_R,INT((E3-sc_b2b_start_R)/sc_b2b_step_R)+1),0) -> 0 | F15: =IF(F3>=sc_b2b_start_R,MIN(sc_b2b_max_R,INT((F3-sc_b2b_start_R)/sc_b2b_step_R)+1),0) -> 1 | G15: =IF(G3>=sc_b2b_start_R,MIN(sc_b2b_max_R,INT((G3-sc_b2b_start_R)/sc_b2b_step_R)+1),0) -> 1 | H15: =IF(H3>=sc_b2b_start_R,MIN(sc_b2b_max_R,INT((H3-sc_b2b_start_R)/sc_b2b_step_R)+1),0) -> 1 | I15: =IF(I3>=sc_b2b_start_R,MIN(sc_b2b_max_R,INT((I3-sc_b2b_start_R)/sc_b2b_step_R)+1),0) -> 2 | J15: =IF(J3>=sc_b2b_start_R,MIN(sc_b2b_max_R,INT((J3-sc_b2b_start_R)/sc_b2b_step_R)+1),0) -> 2 | ... Z15: =IF(Z3>=sc_b2b_start_R,MIN(sc_b2b_max_R,INT((Z3-sc_b2b_start_R)/sc_b2b_step_R)+1),0) -> 5
A16: Потребность в клинерах, FTE | C16: =(C10*UA_man_hours+C13*UB_hours+C14*US_man_hours)/hours_per_fte+C15*b2b_fte -> 1.4279333 | D16: =(D10*UA_man_hours+D13*UB_hours+D14*US_man_hours)/hours_per_fte+D15*b2b_fte -> 2.9138933 | E16: =(E10*UA_man_hours+E13*UB_hours+E14*US_man_hours)/hours_per_fte+E15*b2b_fte -> 2.9009568 | F16: =(F10*UA_man_hours+F13*UB_hours+F14*US_man_hours)/hours_per_fte+F15*b2b_fte -> 5.2538684 | G16: =(G10*UA_man_hours+G13*UB_hours+G14*US_man_hours)/hours_per_fte+G15*b2b_fte -> 7.0190827 | H16: =(H10*UA_man_hours+H13*UB_hours+H14*US_man_hours)/hours_per_fte+H15*b2b_fte -> 9.2906427 | I16: =(I10*UA_man_hours+I13*UB_hours+I14*US_man_hours)/hours_per_fte+I15*b2b_fte -> 11.653959 | J16: =(J10*UA_man_hours+J13*UB_hours+J14*US_man_hours)/hours_per_fte+J15*b2b_fte -> 11.786602 | ... Z16: =(Z10*UA_man_hours+Z13*UB_hours+Z14*US_man_hours)/hours_per_fte+Z15*b2b_fte -> 26.805249
A18: ОПиУ
A19: Выручка A | B19: =SUM(C19:Z19) -> 18905541 | C19: =C10*aov_a -> 153900 | D19: =D10*aov_a -> 301320 | E19: =E10*aov_a -> 238140 | F19: =F10*aov_a -> 343440 | G19: =G10*aov_a -> 492480 | H19: =H10*aov_a -> 698625 | I19: =I10*aov_a -> 789750 | J19: =J10*aov_a -> 722779.2 | ... Z19: =Z10*aov_a -> 1230683.5
A20: Выручка B (подписка) | B20: =SUM(C20:Z20) -> 23261450 | C20: =C13*price_b -> 38438.4 | D20: =D13*price_b -> 92636.544 | E20: =E13*price_b -> 161176.06 | F20: =F13*price_b -> 242766.21 | G20: =G13*price_b -> 336232.45 | H20: =H13*price_b -> 440505.93 | I20: =I13*price_b -> 539430.83 | J20: =J13*price_b -> 633609.6 | ... Z20: =Z13*price_b -> 1835094.9
A21: Выручка S (спецуслуги) | B21: =SUM(C21:Z21) -> 2835831.2 | C21: =C14*aov_s -> 23085 | D21: =D14*aov_s -> 45198 | E21: =E14*aov_s -> 35721 | F21: =F14*aov_s -> 51516 | G21: =G14*aov_s -> 73872 | H21: =H14*aov_s -> 104793.75 | I21: =I14*aov_s -> 118462.5 | J21: =J14*aov_s -> 108416.88 | ... Z21: =Z14*aov_s -> 184602.53
A22: Выручка B2B | B22: =SUM(C22:Z22) -> 4125000 | C22: =C15*b2b_value -> 0 | D22: =D15*b2b_value -> 0 | E22: =E15*b2b_value -> 0 | F22: =F15*b2b_value -> 55000 | G22: =G15*b2b_value -> 55000 | H22: =H15*b2b_value -> 55000 | I22: =I15*b2b_value -> 110000 | J22: =J15*b2b_value -> 110000 | ... Z22: =Z15*b2b_value -> 275000
A23: ВЫРУЧКА | B23: =SUM(C23:Z23) -> 49127822 | C23: =SUM(C19:C22) -> 215423.4 | D23: =SUM(D19:D22) -> 439154.54 | E23: =SUM(E19:E22) -> 435037.06 | F23: =SUM(F19:F22) -> 692722.21 | G23: =SUM(G19:G22) -> 957584.45 | H23: =SUM(H19:H22) -> 1298924.7 | I23: =SUM(I19:I22) -> 1557643.3 | J23: =SUM(J19:J22) -> 1574805.7 | ... Z23: =SUM(Z19:Z22) -> 3525380.9
A24: Переменные затраты (ФОТ клинеров, химия, логистика, эквайринг, резерв) | B24: =SUM(C24:Z24) -> 29631057 | C24: =C10*var_a+C13*var_b+C14*var_s+C15*b2b_direct -> 123507.73 | D24: =D10*var_a+D13*var_b+D14*var_s+D15*b2b_direct -> 252739.1 | E24: =E10*var_a+E13*var_b+E14*var_s+E15*b2b_direct -> 255039.27 | F24: =F10*var_a+F13*var_b+F14*var_s+F15*b2b_direct -> 411700.06 | G24: =G10*var_a+G13*var_b+G14*var_s+G15*b2b_direct -> 566661.15 | H24: =H10*var_a+H13*var_b+H14*var_s+H15*b2b_direct -> 765278.02 | I24: =I10*var_a+I13*var_b+I14*var_s+I15*b2b_direct -> 923685.22 | J24: =J10*var_a+J13*var_b+J14*var_s+J15*b2b_direct -> 939655.24 | ... Z24: =Z10*var_a+Z13*var_b+Z14*var_s+Z15*b2b_direct -> 2134972.2
A25: Валовая прибыль | B25: =SUM(C25:Z25) -> 19496765 | C25: =C23-C24 -> 91915.668 | D25: =D23-D24 -> 186415.44 | E25: =E23-E24 -> 179997.78 | F25: =F23-F24 -> 281022.15 | G25: =G23-G24 -> 390923.3 | H25: =H23-H24 -> 533646.66 | I25: =I23-I24 -> 633958.11 | J25: =J23-J24 -> 635150.44 | ... Z25: =Z23-Z24 -> 1390408.7
A26: Маркетинг (CAC: партнёрам, продвижение, скидка 1-го визита) | B26: =SUM(C26:Z26) -> 3170493.4 | C26: =C10*sc_cac_a_R+C11*sc_cac_b_R+C14*sc_cac_s_R -> 28245 | D26: =D10*sc_cac_a_R+D11*sc_cac_b_R+D14*sc_cac_s_R -> 49806 | E26: =E10*sc_cac_a_R+E11*sc_cac_b_R+E14*sc_cac_s_R -> 49137 | F26: =F10*sc_cac_a_R+F11*sc_cac_b_R+F14*sc_cac_s_R -> 66252 | G26: =G10*sc_cac_a_R+G11*sc_cac_b_R+G14*sc_cac_s_R -> 87984 | H26: =H10*sc_cac_a_R+H11*sc_cac_b_R+H14*sc_cac_s_R -> 115743.75 | I26: =I10*sc_cac_a_R+I11*sc_cac_b_R+I14*sc_cac_s_R -> 126622.5 | J26: =J10*sc_cac_a_R+J11*sc_cac_b_R+J14*sc_cac_s_R -> 120851.16 | ... Z26: =Z10*sc_cac_a_R+Z11*sc_cac_b_R+Z14*sc_cac_s_R -> 201407.67
A27: Постоянные расходы (FIX) | B27: =SUM(C27:Z27) -> 5990400 | C27: =fix_base+fix_step_cost*INT(C23/fix_rev_step) -> 179600 | D27: =fix_base+fix_step_cost*INT(D23/fix_rev_step) -> 179600 | E27: =fix_base+fix_step_cost*INT(E23/fix_rev_step) -> 179600 | F27: =fix_base+fix_step_cost*INT(F23/fix_rev_step) -> 179600 | G27: =fix_base+fix_step_cost*INT(G23/fix_rev_step) -> 179600 | H27: =fix_base+fix_step_cost*INT(H23/fix_rev_step) -> 179600 | I27: =fix_base+fix_step_cost*INT(I23/fix_rev_step) -> 249600 | J27: =fix_base+fix_step_cost*INT(J23/fix_rev_step) -> 249600 | ... Z27: =fix_base+fix_step_cost*INT(Z23/fix_rev_step) -> 319600
A28: НДС применяется (1 = да) | C28: =IF(OR(SUMIFS($C$23:$Z$23,$C$4:$Z$4,C4-1)>vat_threshold,SUMIFS($C$23:$Z$23,$C$4:$Z$4,C4,$C$3:$Z$3,"<"&C3)>vat_threshold),1,0) -> 0 | D28: =IF(OR(SUMIFS($C$23:$Z$23,$C$4:$Z$4,D4-1)>vat_threshold,SUMIFS($C$23:$Z$23,$C$4:$Z$4,D4,$C$3:$Z$3,"<"&D3)>vat_threshold),1,0) -> 0 | E28: =IF(OR(SUMIFS($C$23:$Z$23,$C$4:$Z$4,E4-1)>vat_threshold,SUMIFS($C$23:$Z$23,$C$4:$Z$4,E4,$C$3:$Z$3,"<"&E3)>vat_threshold),1,0) -> 0 | F28: =IF(OR(SUMIFS($C$23:$Z$23,$C$4:$Z$4,F4-1)>vat_threshold,SUMIFS($C$23:$Z$23,$C$4:$Z$4,F4,$C$3:$Z$3,"<"&F3)>vat_threshold),1,0) -> 0 | G28: =IF(OR(SUMIFS($C$23:$Z$23,$C$4:$Z$4,G4-1)>vat_threshold,SUMIFS($C$23:$Z$23,$C$4:$Z$4,G4,$C$3:$Z$3,"<"&G3)>vat_threshold),1,0) -> 0 | H28: =IF(OR(SUMIFS($C$23:$Z$23,$C$4:$Z$4,H4-1)>vat_threshold,SUMIFS($C$23:$Z$23,$C$4:$Z$4,H4,$C$3:$Z$3,"<"&H3)>vat_threshold),1,0) -> 0 | I28: =IF(OR(SUMIFS($C$23:$Z$23,$C$4:$Z$4,I4-1)>vat_threshold,SUMIFS($C$23:$Z$23,$C$4:$Z$4,I4,$C$3:$Z$3,"<"&I3)>vat_threshold),1,0) -> 0 | J28: =IF(OR(SUMIFS($C$23:$Z$23,$C$4:$Z$4,J4-1)>vat_threshold,SUMIFS($C$23:$Z$23,$C$4:$Z$4,J4,$C$3:$Z$3,"<"&J3)>vat_threshold),1,0) -> 0 | ... Z28: =IF(OR(SUMIFS($C$23:$Z$23,$C$4:$Z$4,Z4-1)>vat_threshold,SUMIFS($C$23:$Z$23,$C$4:$Z$4,Z4,$C$3:$Z$3,"<"&Z3)>vat_threshold),1,0) -> 1
A29: НДС (выделяется из цены) | B29: =SUM(C29:Z29) -> 336296.1 | C29: =C23*vat_rate/(1+vat_rate)*C28 -> 0 | D29: =D23*vat_rate/(1+vat_rate)*D28 -> 0 | E29: =E23*vat_rate/(1+vat_rate)*E28 -> 0 | F29: =F23*vat_rate/(1+vat_rate)*F28 -> 0 | G29: =G23*vat_rate/(1+vat_rate)*G28 -> 0 | H29: =H23*vat_rate/(1+vat_rate)*H28 -> 0 | I29: =I23*vat_rate/(1+vat_rate)*I28 -> 0 | J29: =J23*vat_rate/(1+vat_rate)*J28 -> 0 | ... Z29: =Z23*vat_rate/(1+vat_rate)*Z28 -> 167875.28
A30: УСН | B30: =SUM(C30:Z30) -> 2927491.6 | C30: =(C23-C29)*usn_rate -> 12925.404 | D30: =(D23-D29)*usn_rate -> 26349.273 | E30: =(E23-E29)*usn_rate -> 26102.223 | F30: =(F23-F29)*usn_rate -> 41563.333 | G30: =(G23-G29)*usn_rate -> 57455.067 | H30: =(H23-H29)*usn_rate -> 77935.481 | I30: =(I23-I29)*usn_rate -> 93458.6 | J30: =(J23-J29)*usn_rate -> 94488.341 | ... Z30: =(Z23-Z29)*usn_rate -> 201450.34
A31: ОПЕРАЦИОННАЯ ПРИБЫЛЬ | B31: =SUM(C31:Z31) -> 7072084.3 | C31: =C23-C29-C24-C26-C27-C30 -> -128854.74 | D31: =D23-D29-D24-D26-D27-D30 -> -69339.83 | E31: =E23-E29-E24-E26-E27-E30 -> -74841.442 | F31: =F23-F29-F24-F26-F27-F30 -> -6393.1817 | G31: =G23-G29-G24-G26-G27-G30 -> 65884.235 | H31: =H23-H29-H24-H26-H27-H30 -> 160367.43 | I31: =I23-I29-I24-I26-I27-I30 -> 164277.01 | J31: =J23-J29-J24-J26-J27-J30 -> 170210.94 | ... Z31: =Z23-Z29-Z24-Z26-Z27-Z30 -> 500075.43
A32: Рентабельность по операционной прибыли | B32: =IF(B23=0,0,B31/B23) -> 0.14395273 | C32: =IF(C23=0,0,C31/C23) -> -0.59814642 | D32: =IF(D23=0,0,D31/D23) -> -0.15789391 | E32: =IF(E23=0,0,E31/E23) -> -0.17203464 | F32: =IF(F23=0,0,F31/F23) -> -0.0092290699 | G32: =IF(G23=0,0,G31/G23) -> 0.068802532 | H32: =IF(H23=0,0,H31/H23) -> 0.12346169 | I32: =IF(I23=0,0,I31/I23) -> 0.1054651 | ... Z32: =IF(Z23=0,0,Z31/Z23) -> 0.14185004
A34: ДЕНЕЖНЫЙ ПОТОК
A35: CAPEX 2-го этапа | B35: =SUM(C35:Z35) -> 335000 | C35: =IF(C3=sc_capex2_month_R,capex2_total,0) -> 0 | D35: =IF(D3=sc_capex2_month_R,capex2_total,0) -> 0 | E35: =IF(E3=sc_capex2_month_R,capex2_total,0) -> 0 | F35: =IF(F3=sc_capex2_month_R,capex2_total,0) -> 0 | G35: =IF(G3=sc_capex2_month_R,capex2_total,0) -> 0 | H35: =IF(H3=sc_capex2_month_R,capex2_total,0) -> 335000 | I35: =IF(I3=sc_capex2_month_R,capex2_total,0) -> 0 | J35: =IF(J3=sc_capex2_month_R,capex2_total,0) -> 0 | ... Z35: =IF(Z3=sc_capex2_month_R,capex2_total,0) -> 0
A36: Денежный поток месяца | B36: =SUM(C36:Z36) -> 6737084.3 | C36: =C31-C35 -> -128854.74 | D36: =D31-D35 -> -69339.83 | E36: =E31-E35 -> -74841.442 | F36: =F31-F35 -> -6393.1817 | G36: =G31-G35 -> 65884.235 | H36: =H31-H35 -> -174632.57 | I36: =I31-I35 -> 164277.01 | J36: =J31-J35 -> 170210.94 | ... Z36: =Z31-Z35 -> 500075.43
A37: Накопленный ДП без стартовых вложений | C37: =C36 -> -128854.74 | D37: =C37+D36 -> -198194.57 | E37: =D37+E36 -> -273036.01 | F37: =E37+F36 -> -279429.19 | G37: =F37+G36 -> -213544.95 | H37: =G37+H36 -> -388177.52 | I37: =H37+I36 -> -223900.52 | J37: =I37+J36 -> -53689.578 | K37: =J37+K36 -> 107652.92 | ... Z37: =Y37+Z36 -> 6737084.3
A38: Накопленный ДП с учётом CAPEX и предзапуска (M0) | C38: =-(capex_base+prelaunch_total)+C36 -> -702854.74 | D38: =C38+D36 -> -772194.57 | E38: =D38+E36 -> -847036.01 | F38: =E38+F36 -> -853429.19 | G38: =F38+G36 -> -787544.95 | H38: =G38+H36 -> -962177.52 | I38: =H38+I36 -> -797900.52 | J38: =I38+J36 -> -627689.58 | K38: =J38+K36 -> -466347.08 | ... Z38: =Y38+Z36 -> 6163084.3
A39: Служебная: месяц, после которого нет убыточных месяцев | C39: =IF(COUNTIF(C31:$Z$31,"<0")=0,C3,"") | D39: =IF(COUNTIF(D31:$Z$31,"<0")=0,D3,"") | E39: =IF(COUNTIF(E31:$Z$31,"<0")=0,E3,"") | F39: =IF(COUNTIF(F31:$Z$31,"<0")=0,F3,"") | G39: =IF(COUNTIF(G31:$Z$31,"<0")=0,G3,"") -> 5 | H39: =IF(COUNTIF(H31:$Z$31,"<0")=0,H3,"") -> 6 | I39: =IF(COUNTIF(I31:$Z$31,"<0")=0,I3,"") -> 7 | J39: =IF(COUNTIF(J31:$Z$31,"<0")=0,J3,"") -> 8 | ... Z39: =IF(COUNTIF(Z31:$Z$31,"<0")=0,Z3,"") -> 24

Sheet ОПиУ_Оптимист
A1: ОПиУ и денежный поток — сценарий «Оптимистичный», ₽
A2: Показатель | B2: Итого 24 мес | C2: M1 ноя 26 | D2: M2 дек 26 | E2: M3 янв 27 | F2: M4 фев 27 | G2: M5 мар 27 | H2: M6 апр 27 | I2: M7 май 27 | J2: M8 июн 27 | K2: M9 июл 27 | L2: M10 авг 27 | M2: M11 сен 27 | N2: M12 окт 27 | O2: M13 ноя 27 | P2: M14 дек 27 | Q2: M15 янв 28 | R2: M16 фев 28 | S2: M17 мар 28 | T2: M18 апр 28 | U2: M19 май 28 | V2: M20 июн 28 | W2: M21 июл 28 | X2: M22 авг 28 | Y2: M23 сен 28 | Z2: M24 окт 28
A3: Месяц № | C3: 1 | D3: 2 | E3: 3 | F3: 4 | G3: 5 | H3: 6 | I3: 7 | J3: 8 | K3: 9 | L3: 10 | M3: 11 | N3: 12 | O3: 13 | P3: 14 | Q3: 15 | R3: 16 | S3: 17 | T3: 18 | U3: 19 | V3: 20 | W3: 21 | X3: 22 | Y3: 23 | Z3: 24
A4: Год | C4: =start_year+INT((start_month-1+C3-1)/12) -> 2026 | D4: =start_year+INT((start_month-1+D3-1)/12) -> 2026 | E4: =start_year+INT((start_month-1+E3-1)/12) -> 2027 | F4: =start_year+INT((start_month-1+F3-1)/12) -> 2027 | G4: =start_year+INT((start_month-1+G3-1)/12) -> 2027 | H4: =start_year+INT((start_month-1+H3-1)/12) -> 2027 | I4: =start_year+INT((start_month-1+I3-1)/12) -> 2027 | J4: =start_year+INT((start_month-1+J3-1)/12) -> 2027 | ... Z4: =start_year+INT((start_month-1+Z3-1)/12) -> 2028
A5: Календарный месяц | C5: =MOD(start_month-1+C3-1,12)+1 -> 11 | D5: =MOD(start_month-1+D3-1,12)+1 -> 12 | E5: =MOD(start_month-1+E3-1,12)+1 -> 1 | F5: =MOD(start_month-1+F3-1,12)+1 -> 2 | G5: =MOD(start_month-1+G3-1,12)+1 -> 3 | H5: =MOD(start_month-1+H3-1,12)+1 -> 4 | I5: =MOD(start_month-1+I3-1,12)+1 -> 5 | J5: =MOD(start_month-1+J3-1,12)+1 -> 6 | ... Z5: =MOD(start_month-1+Z3-1,12)+1 -> 10
A6: Индекс сезонности | C6: =INDEX(season_tbl,C5) -> 0.95 | D6: =INDEX(season_tbl,D5) -> 1.2 | E6: =INDEX(season_tbl,E5) -> 0.7 | F6: =INDEX(season_tbl,F5) -> 0.8 | G6: =INDEX(season_tbl,G5) -> 0.95 | H6: =INDEX(season_tbl,H5) -> 1.15 | I6: =INDEX(season_tbl,I5) -> 1.25 | J6: =INDEX(season_tbl,J5) -> 1.1 | ... Z6: =INDEX(season_tbl,Z5) -> 1
A8: ОБЪЁМЫ
A9: Заказы A до сезонности | C9: =IF(C3<=6,sc_a_start_O+(sc_a_m6_O-sc_a_start_O)*(C3-1)/5,sc_a_m6_O*(1+sc_a_growth_O)^(C3-6)) -> 18 | D9: =IF(D3<=6,sc_a_start_O+(sc_a_m6_O-sc_a_start_O)*(D3-1)/5,sc_a_m6_O*(1+sc_a_growth_O)^(D3-6)) -> 26.4 | E9: =IF(E3<=6,sc_a_start_O+(sc_a_m6_O-sc_a_start_O)*(E3-1)/5,sc_a_m6_O*(1+sc_a_growth_O)^(E3-6)) -> 34.8 | F9: =IF(F3<=6,sc_a_start_O+(sc_a_m6_O-sc_a_start_O)*(F3-1)/5,sc_a_m6_O*(1+sc_a_growth_O)^(F3-6)) -> 43.2 | G9: =IF(G3<=6,sc_a_start_O+(sc_a_m6_O-sc_a_start_O)*(G3-1)/5,sc_a_m6_O*(1+sc_a_growth_O)^(G3-6)) -> 51.6 | H9: =IF(H3<=6,sc_a_start_O+(sc_a_m6_O-sc_a_start_O)*(H3-1)/5,sc_a_m6_O*(1+sc_a_growth_O)^(H3-6)) -> 60 | I9: =IF(I3<=6,sc_a_start_O+(sc_a_m6_O-sc_a_start_O)*(I3-1)/5,sc_a_m6_O*(1+sc_a_growth_O)^(I3-6)) -> 63 | J9: =IF(J3<=6,sc_a_start_O+(sc_a_m6_O-sc_a_start_O)*(J3-1)/5,sc_a_m6_O*(1+sc_a_growth_O)^(J3-6)) -> 66.15 | ... Z9: =IF(Z3<=6,sc_a_start_O+(sc_a_m6_O-sc_a_start_O)*(Z3-1)/5,sc_a_m6_O*(1+sc_a_growth_O)^(Z3-6)) -> 144.39715
A10: Заказы A (генеральная / после ремонта) | B10: =SUM(C10:Z10) -> 2032.7503 | C10: =MIN(sc_a_cap_O,C9*C6) -> 17.1 | D10: =MIN(sc_a_cap_O,D9*D6) -> 31.68 | E10: =MIN(sc_a_cap_O,E9*E6) -> 24.36 | F10: =MIN(sc_a_cap_O,F9*F6) -> 34.56 | G10: =MIN(sc_a_cap_O,G9*G6) -> 49.02 | H10: =MIN(sc_a_cap_O,H9*H6) -> 69 | I10: =MIN(sc_a_cap_O,I9*I6) -> 78.75 | J10: =MIN(sc_a_cap_O,J9*J6) -> 72.765 | ... Z10: =MIN(sc_a_cap_O,Z9*Z6) -> 140
A11: Новые подписчики B | B11: =SUM(C11:Z11) -> 585.14361 | C11: =IF(C3<=6,sc_s_start_O+(sc_s_m6_O-sc_s_start_O)*(C3-1)/5,sc_s_m6_O*(1+sc_s_growth_O)^(C3-6)) -> 6 | D11: =IF(D3<=6,sc_s_start_O+(sc_s_m6_O-sc_s_start_O)*(D3-1)/5,sc_s_m6_O*(1+sc_s_growth_O)^(D3-6)) -> 8.8 | E11: =IF(E3<=6,sc_s_start_O+(sc_s_m6_O-sc_s_start_O)*(E3-1)/5,sc_s_m6_O*(1+sc_s_growth_O)^(E3-6)) -> 11.6 | F11: =IF(F3<=6,sc_s_start_O+(sc_s_m6_O-sc_s_start_O)*(F3-1)/5,sc_s_m6_O*(1+sc_s_growth_O)^(F3-6)) -> 14.4 | G11: =IF(G3<=6,sc_s_start_O+(sc_s_m6_O-sc_s_start_O)*(G3-1)/5,sc_s_m6_O*(1+sc_s_growth_O)^(G3-6)) -> 17.2 | H11: =IF(H3<=6,sc_s_start_O+(sc_s_m6_O-sc_s_start_O)*(H3-1)/5,sc_s_m6_O*(1+sc_s_growth_O)^(H3-6)) -> 20 | I11: =IF(I3<=6,sc_s_start_O+(sc_s_m6_O-sc_s_start_O)*(I3-1)/5,sc_s_m6_O*(1+sc_s_growth_O)^(I3-6)) -> 20.7 | J11: =IF(J3<=6,sc_s_start_O+(sc_s_m6_O-sc_s_start_O)*(J3-1)/5,sc_s_m6_O*(1+sc_s_growth_O)^(J3-6)) -> 21.4245 | ... Z11: =IF(Z3<=6,sc_s_start_O+(sc_s_m6_O-sc_s_start_O)*(Z3-1)/5,sc_s_m6_O*(1+sc_s_growth_O)^(Z3-6)) -> 37.149784
A12: Активные подписчики B | C12: =C11 -> 6 | D12: =C12*(1-sc_churn_O)+D11 -> 14.38 | E12: =D12*(1-sc_churn_O)+E11 -> 24.9734 | F12: =E12*(1-sc_churn_O)+F11 -> 37.625262 | G12: =F12*(1-sc_churn_O)+G11 -> 52.191494 | H12: =G12*(1-sc_churn_O)+H11 -> 68.538089 | I12: =H12*(1-sc_churn_O)+I11 -> 84.440423 | J12: =I12*(1-sc_churn_O)+J11 -> 99.954093 | K12: =J12*(1-sc_churn_O)+K11 -> 115.13166 | ... Z12: =Y12*(1-sc_churn_O)+Z11 -> 331.36099
A13: Визиты B | B13: =SUM(C13:Z13) -> 11079.115 | C13: =C12*UB_visits_per_month -> 16.8 | D13: =D12*UB_visits_per_month -> 40.264 | E13: =E12*UB_visits_per_month -> 69.92552 | F13: =F12*UB_visits_per_month -> 105.35073 | G13: =G12*UB_visits_per_month -> 146.13618 | H13: =H12*UB_visits_per_month -> 191.90665 | I13: =I12*UB_visits_per_month -> 236.43318 | J13: =J12*UB_visits_per_month -> 279.87146 | ... Z13: =Z12*UB_visits_per_month -> 927.81078
A14: Заказы спецуслуг S | B14: =SUM(C14:Z14) -> 1219.6502 | C14: =C10*sc_spec_ratio_O -> 10.26 | D14: =D10*sc_spec_ratio_O -> 19.008 | E14: =E10*sc_spec_ratio_O -> 14.616 | F14: =F10*sc_spec_ratio_O -> 20.736 | G14: =G10*sc_spec_ratio_O -> 29.412 | H14: =H10*sc_spec_ratio_O -> 41.4 | I14: =I10*sc_spec_ratio_O -> 47.25 | J14: =J10*sc_spec_ratio_O -> 43.659 | ... Z14: =Z10*sc_spec_ratio_O -> 84
A15: Действующие B2B-договоры | C15: =IF(C3>=sc_b2b_start_O,MIN(sc_b2b_max_O,INT((C3-sc_b2b_start_O)/sc_b2b_step_O)+1),0) -> 0 | D15: =IF(D3>=sc_b2b_start_O,MIN(sc_b2b_max_O,INT((D3-sc_b2b_start_O)/sc_b2b_step_O)+1),0) -> 0 | E15: =IF(E3>=sc_b2b_start_O,MIN(sc_b2b_max_O,INT((E3-sc_b2b_start_O)/sc_b2b_step_O)+1),0) -> 1 | F15: =IF(F3>=sc_b2b_start_O,MIN(sc_b2b_max_O,INT((F3-sc_b2b_start_O)/sc_b2b_step_O)+1),0) -> 1 | G15: =IF(G3>=sc_b2b_start_O,MIN(sc_b2b_max_O,INT((G3-sc_b2b_start_O)/sc_b2b_step_O)+1),0) -> 2 | H15: =IF(H3>=sc_b2b_start_O,MIN(sc_b2b_max_O,INT((H3-sc_b2b_start_O)/sc_b2b_step_O)+1),0) -> 2 | I15: =IF(I3>=sc_b2b_start_O,MIN(sc_b2b_max_O,INT((I3-sc_b2b_start_O)/sc_b2b_step_O)+1),0) -> 3 | J15: =IF(J3>=sc_b2b_start_O,MIN(sc_b2b_max_O,INT((J3-sc_b2b_start_O)/sc_b2b_step_O)+1),0) -> 3 | ... Z15: =IF(Z3>=sc_b2b_start_O,MIN(sc_b2b_max_O,INT((Z3-sc_b2b_start_O)/sc_b2b_step_O)+1),0) -> 7
A16: Потребность в клинерах, FTE | C16: =(C10*UA_man_hours+C13*UB_hours+C14*US_man_hours)/hours_per_fte+C15*b2b_fte -> 2.1932 | D16: =(D10*UA_man_hours+D13*UB_hours+D14*US_man_hours)/hours_per_fte+D15*b2b_fte -> 4.2764533 | E16: =(E10*UA_man_hours+E13*UB_hours+E14*US_man_hours)/hours_per_fte+E15*b2b_fte -> 5.1975155 | F16: =(F10*UA_man_hours+F13*UB_hours+F14*US_man_hours)/hours_per_fte+F15*b2b_fte -> 7.0985038 | G16: =(G10*UA_man_hours+G13*UB_hours+G14*US_man_hours)/hours_per_fte+G15*b2b_fte -> 10.573284 | H16: =(H10*UA_man_hours+H13*UB_hours+H14*US_man_hours)/hours_per_fte+H15*b2b_fte -> 13.745822 | I16: =(I10*UA_man_hours+I13*UB_hours+I14*US_man_hours)/hours_per_fte+I15*b2b_fte -> 16.811774 | J16: =(J10*UA_man_hours+J13*UB_hours+J14*US_man_hours)/hours_per_fte+J15*b2b_fte -> 17.194914 | ... Z16: =(Z10*UA_man_hours+Z13*UB_hours+Z14*US_man_hours)/hours_per_fte+Z15*b2b_fte -> 43.395585
A18: ОПиУ
A19: Выручка A | B19: =SUM(C19:Z19) -> 27442130 | C19: =C10*aov_a -> 230850 | D19: =D10*aov_a -> 427680 | E19: =E10*aov_a -> 328860 | F19: =F10*aov_a -> 466560 | G19: =G10*aov_a -> 661770 | H19: =H10*aov_a -> 931500 | I19: =I10*aov_a -> 1063125 | J19: =J10*aov_a -> 982327.5 | ... Z19: =Z10*aov_a -> 1890000
A20: Выручка B (подписка) | B20: =SUM(C20:Z20) -> 38023524 | C20: =C13*price_b -> 57657.6 | D20: =D13*price_b -> 138186.05 | E20: =E13*price_b -> 239984.38 | F20: =F13*price_b -> 361563.72 | G20: =G13*price_b -> 501539.38 | H20: =H13*price_b -> 658623.62 | I20: =I13*price_b -> 811438.69 | J20: =J13*price_b -> 960518.85 | ... Z20: =Z13*price_b -> 3184246.6
A21: Выручка S (спецуслуги) | B21: =SUM(C21:Z21) -> 5488425.9 | C21: =C14*aov_s -> 46170 | D21: =D14*aov_s -> 85536 | E21: =E14*aov_s -> 65772 | F21: =F14*aov_s -> 93312 | G21: =G14*aov_s -> 132354 | H21: =H14*aov_s -> 186300 | I21: =I14*aov_s -> 212625 | J21: =J14*aov_s -> 196465.5 | ... Z21: =Z14*aov_s -> 378000
A22: Выручка B2B | B22: =SUM(C22:Z22) -> 6160000 | C22: =C15*b2b_value -> 0 | D22: =D15*b2b_value -> 0 | E22: =E15*b2b_value -> 55000 | F22: =F15*b2b_value -> 55000 | G22: =G15*b2b_value -> 110000 | H22: =H15*b2b_value -> 110000 | I22: =I15*b2b_value -> 165000 | J22: =J15*b2b_value -> 165000 | ... Z22: =Z15*b2b_value -> 385000
A23: ВЫРУЧКА | B23: =SUM(C23:Z23) -> 77114080 | C23: =SUM(C19:C22) -> 334677.6 | D23: =SUM(D19:D22) -> 651402.05 | E23: =SUM(E19:E22) -> 689616.38 | F23: =SUM(F19:F22) -> 976435.72 | G23: =SUM(G19:G22) -> 1405663.4 | H23: =SUM(H19:H22) -> 1886423.6 | I23: =SUM(I19:I22) -> 2252188.7 | J23: =SUM(J19:J22) -> 2304311.9 | ... Z23: =SUM(Z19:Z22) -> 5837246.6
A24: Переменные затраты (ФОТ клинеров, химия, логистика, эквайринг, резерв) | B24: =SUM(C24:Z24) -> 46646402 | C24: =C10*var_a+C13*var_b+C14*var_s+C15*b2b_direct -> 192341 | D24: =D10*var_a+D13*var_b+D14*var_s+D15*b2b_direct -> 376054.82 | E24: =E10*var_a+E13*var_b+E14*var_s+E15*b2b_direct -> 410624.78 | F24: =F10*var_a+F13*var_b+F14*var_s+F15*b2b_direct -> 580160.42 | G24: =G10*var_a+G13*var_b+G14*var_s+G15*b2b_direct -> 837547.42 | H24: =H10*var_a+H13*var_b+H14*var_s+H15*b2b_direct -> 1118678.2 | I24: =I10*var_a+I13*var_b+I14*var_s+I15*b2b_direct -> 1341140.9 | J24: =J10*var_a+J13*var_b+J14*var_s+J15*b2b_direct -> 1380218.8 | ... Z24: =Z10*var_a+Z13*var_b+Z14*var_s+Z15*b2b_direct -> 3541411.9
A25: Валовая прибыль | B25: =SUM(C25:Z25) -> 30467678 | C25: =C23-C24 -> 142336.6 | D25: =D23-D24 -> 275347.22 | E25: =E23-E24 -> 278991.6 | F25: =F23-F24 -> 396275.3 | G25: =G23-G24 -> 568115.95 | H25: =H23-H24 -> 767745.39 | I25: =I23-I24 -> 911047.82 | J25: =J23-J24 -> 924093.06 | ... Z25: =Z23-Z24 -> 2295834.7
A26: Маркетинг (CAC: партнёрам, продвижение, скидка 1-го визита) | B26: =SUM(C26:Z26) -> 3983469.5 | C26: =C10*sc_cac_a_O+C11*sc_cac_b_O+C14*sc_cac_s_O -> 36204 | D26: =D10*sc_cac_a_O+D11*sc_cac_b_O+D14*sc_cac_s_O -> 61283.2 | E26: =E10*sc_cac_a_O+E11*sc_cac_b_O+E14*sc_cac_s_O -> 59206.4 | F26: =F10*sc_cac_a_O+F11*sc_cac_b_O+F14*sc_cac_s_O -> 78854.4 | G26: =G10*sc_cac_a_O+G11*sc_cac_b_O+G14*sc_cac_s_O -> 103784.8 | H26: =H10*sc_cac_a_O+H11*sc_cac_b_O+H14*sc_cac_s_O -> 135560 | I26: =I10*sc_cac_a_O+I11*sc_cac_b_O+I14*sc_cac_s_O -> 149400 | J26: =J10*sc_cac_a_O+J11*sc_cac_b_O+J14*sc_cac_s_O -> 143789.85 | ... Z26: =Z10*sc_cac_a_O+Z11*sc_cac_b_O+Z14*sc_cac_s_O -> 266474.46
A27: Постоянные расходы (FIX) | B27: =SUM(C27:Z27) -> 7110400 | C27: =fix_base+fix_step_cost*INT(C23/fix_rev_step) -> 179600 | D27: =fix_base+fix_step_cost*INT(D23/fix_rev_step) -> 179600 | E27: =fix_base+fix_step_cost*INT(E23/fix_rev_step) -> 179600 | F27: =fix_base+fix_step_cost*INT(F23/fix_rev_step) -> 179600 | G27: =fix_base+fix_step_cost*INT(G23/fix_rev_step) -> 179600 | H27: =fix_base+fix_step_cost*INT(H23/fix_rev_step) -> 249600 | I27: =fix_base+fix_step_cost*INT(I23/fix_rev_step) -> 249600 | J27: =fix_base+fix_step_cost*INT(J23/fix_rev_step) -> 249600 | ... Z27: =fix_base+fix_step_cost*INT(Z23/fix_rev_step) -> 389600
A28: НДС применяется (1 = да) | C28: =IF(OR(SUMIFS($C$23:$Z$23,$C$4:$Z$4,C4-1)>vat_threshold,SUMIFS($C$23:$Z$23,$C$4:$Z$4,C4,$C$3:$Z$3,"<"&C3)>vat_threshold),1,0) -> 0 | D28: =IF(OR(SUMIFS($C$23:$Z$23,$C$4:$Z$4,D4-1)>vat_threshold,SUMIFS($C$23:$Z$23,$C$4:$Z$4,D4,$C$3:$Z$3,"<"&D3)>vat_threshold),1,0) -> 0 | E28: =IF(OR(SUMIFS($C$23:$Z$23,$C$4:$Z$4,E4-1)>vat_threshold,SUMIFS($C$23:$Z$23,$C$4:$Z$4,E4,$C$3:$Z$3,"<"&E3)>vat_threshold),1,0) -> 0 | F28: =IF(OR(SUMIFS($C$23:$Z$23,$C$4:$Z$4,F4-1)>vat_threshold,SUMIFS($C$23:$Z$23,$C$4:$Z$4,F4,$C$3:$Z$3,"<"&F3)>vat_threshold),1,0) -> 0 | G28: =IF(OR(SUMIFS($C$23:$Z$23,$C$4:$Z$4,G4-1)>vat_threshold,SUMIFS($C$23:$Z$23,$C$4:$Z$4,G4,$C$3:$Z$3,"<"&G3)>vat_threshold),1,0) -> 0 | H28: =IF(OR(SUMIFS($C$23:$Z$23,$C$4:$Z$4,H4-1)>vat_threshold,SUMIFS($C$23:$Z$23,$C$4:$Z$4,H4,$C$3:$Z$3,"<"&H3)>vat_threshold),1,0) -> 0 | I28: =IF(OR(SUMIFS($C$23:$Z$23,$C$4:$Z$4,I4-1)>vat_threshold,SUMIFS($C$23:$Z$23,$C$4:$Z$4,I4,$C$3:$Z$3,"<"&I3)>vat_threshold),1,0) -> 0 | J28: =IF(OR(SUMIFS($C$23:$Z$23,$C$4:$Z$4,J4-1)>vat_threshold,SUMIFS($C$23:$Z$23,$C$4:$Z$4,J4,$C$3:$Z$3,"<"&J3)>vat_threshold),1,0) -> 0 | ... Z28: =IF(OR(SUMIFS($C$23:$Z$23,$C$4:$Z$4,Z4-1)>vat_threshold,SUMIFS($C$23:$Z$23,$C$4:$Z$4,Z4,$C$3:$Z$3,"<"&Z3)>vat_threshold),1,0) -> 1
A29: НДС (выделяется из цены) | B29: =SUM(C29:Z29) -> 2639411.5 | C29: =C23*vat_rate/(1+vat_rate)*C28 -> 0 | D29: =D23*vat_rate/(1+vat_rate)*D28 -> 0 | E29: =E23*vat_rate/(1+vat_rate)*E28 -> 0 | F29: =F23*vat_rate/(1+vat_rate)*F28 -> 0 | G29: =G23*vat_rate/(1+vat_rate)*G28 -> 0 | H29: =H23*vat_rate/(1+vat_rate)*H28 -> 0 | I29: =I23*vat_rate/(1+vat_rate)*I28 -> 0 | J29: =J23*vat_rate/(1+vat_rate)*J28 -> 0 | ... Z29: =Z23*vat_rate/(1+vat_rate)*Z28 -> 277964.12
A30: УСН | B30: =SUM(C30:Z30) -> 4468480.1 | C30: =(C23-C29)*usn_rate -> 20080.656 | D30: =(D23-D29)*usn_rate -> 39084.123 | E30: =(E23-E29)*usn_rate -> 41376.983 | F30: =(F23-F29)*usn_rate -> 58586.143 | G30: =(G23-G29)*usn_rate -> 84339.803 | H30: =(H23-H29)*usn_rate -> 113185.42 | I30: =(I23-I29)*usn_rate -> 135131.32 | J30: =(J23-J29)*usn_rate -> 138258.71 | ... Z30: =(Z23-Z29)*usn_rate -> 333556.95
A31: ОПЕРАЦИОННАЯ ПРИБЫЛЬ | B31: =SUM(C31:Z31) -> 12265917 | C31: =C23-C29-C24-C26-C27-C30 -> -93548.054 | D31: =D23-D29-D24-D26-D27-D30 -> -4620.0979 | E31: =E23-E29-E24-E26-E27-E30 -> -1191.7783 | F31: =F23-F29-F24-F26-F27-F30 -> 79234.756 | G31: =G23-G29-G24-G26-G27-G30 -> 200391.35 | H31: =H23-H29-H24-H26-H27-H30 -> 269399.97 | I31: =I23-I29-I24-I26-I27-I30 -> 376916.5 | J31: =J23-J29-J24-J26-J27-J30 -> 392444.5 | ... Z31: =Z23-Z29-Z24-Z26-Z27-Z30 -> 1028239.2
A32: Рентабельность по операционной прибыли | B32: =IF(B23=0,0,B31/B23) -> 0.15906196 | C32: =IF(C23=0,0,C31/C23) -> -0.27951693 | D32: =IF(D23=0,0,D31/D23) -> -0.0070925444 | E32: =IF(E23=0,0,E31/E23) -> -0.0017281757 | F32: =IF(F23=0,0,F31/F23) -> 0.081146925 | G32: =IF(G23=0,0,G31/G23) -> 0.14255999 | H32: =IF(H23=0,0,H31/H23) -> 0.1428099 | I32: =IF(I23=0,0,I31/I23) -> 0.16735565 | ... Z32: =IF(Z23=0,0,Z31/Z23) -> 0.17615141
A34: ДЕНЕЖНЫЙ ПОТОК
A35: CAPEX 2-го этапа | B35: =SUM(C35:Z35) -> 335000 | C35: =IF(C3=sc_capex2_month_O,capex2_total,0) -> 0 | D35: =IF(D3=sc_capex2_month_O,capex2_total,0) -> 0 | E35: =IF(E3=sc_capex2_month_O,capex2_total,0) -> 0 | F35: =IF(F3=sc_capex2_month_O,capex2_total,0) -> 335000 | G35: =IF(G3=sc_capex2_month_O,capex2_total,0) -> 0 | H35: =IF(H3=sc_capex2_month_O,capex2_total,0) -> 0 | I35: =IF(I3=sc_capex2_month_O,capex2_total,0) -> 0 | J35: =IF(J3=sc_capex2_month_O,capex2_total,0) -> 0 | ... Z35: =IF(Z3=sc_capex2_month_O,capex2_total,0) -> 0
A36: Денежный поток месяца | B36: =SUM(C36:Z36) -> 11930917 | C36: =C31-C35 -> -93548.054 | D36: =D31-D35 -> -4620.0979 | E36: =E31-E35 -> -1191.7783 | F36: =F31-F35 -> -255765.24 | G36: =G31-G35 -> 200391.35 | H36: =H31-H35 -> 269399.97 | I36: =I31-I35 -> 376916.5 | J36: =J31-J35 -> 392444.5 | ... Z36: =Z31-Z35 -> 1028239.2
A37: Накопленный ДП без стартовых вложений | C37: =C36 -> -93548.054 | D37: =C37+D36 -> -98168.152 | E37: =D37+E36 -> -99359.93 | F37: =E37+F36 -> -355125.17 | G37: =F37+G36 -> -154733.82 | H37: =G37+H36 -> 114666.15 | I37: =H37+I36 -> 491582.65 | J37: =I37+J36 -> 884027.14 | K37: =J37+K36 -> 1284488.9 | ... Z37: =Y37+Z36 -> 11930917
A38: Накопленный ДП с учётом CAPEX и предзапуска (M0) | C38: =-(capex_base+prelaunch_total)+C36 -> -667548.05 | D38: =C38+D36 -> -672168.15 | E38: =D38+E36 -> -673359.93 | F38: =E38+F36 -> -929125.17 | G38: =F38+G36 -> -728733.82 | H38: =G38+H36 -> -459333.85 | I38: =H38+I36 -> -82417.352 | J38: =I38+J36 -> 310027.14 | K38: =J38+K36 -> 710488.93 | ... Z38: =Y38+Z36 -> 11356917
A39: Служебная: месяц, после которого нет убыточных месяцев | C39: =IF(COUNTIF(C31:$Z$31,"<0")=0,C3,"") | D39: =IF(COUNTIF(D31:$Z$31,"<0")=0,D3,"") | E39: =IF(COUNTIF(E31:$Z$31,"<0")=0,E3,"") | F39: =IF(COUNTIF(F31:$Z$31,"<0")=0,F3,"") -> 4 | G39: =IF(COUNTIF(G31:$Z$31,"<0")=0,G3,"") -> 5 | H39: =IF(COUNTIF(H31:$Z$31,"<0")=0,H3,"") -> 6 | I39: =IF(COUNTIF(I31:$Z$31,"<0")=0,I3,"") -> 7 | J39: =IF(COUNTIF(J31:$Z$31,"<0")=0,J3,"") -> 8 | ... Z39: =IF(COUNTIF(Z31:$Z$31,"<0")=0,Z3,"") -> 24
